[{ "url":"http://vectorbest.ru",
"callback":"qwerty"}
,{ "url":"http://тачки41.рф",
"callback":"qwerty"}
,{ "url":"http://www.avto-navi.ru",
"callback":"qwerty"}
,{ "url":"http://www.vl-logistic.ru",
"callback":"qwerty"}
,{ "url":"http://www.airport-pkc.ru",
"callback":"qwerty"}
,{ "url":"http://41port.ru",
"callback":"qwerty"}
,{ "url":"http://eastbreeze41.wordpress.com",
"callback":"qwerty"}
,{ "url":"http://virtus-china.ru",
"callback":"qwerty"}
,{ "url":"http://kamgilservisplus.ru",
"callback":"qwerty"}
,{ "url":"http://www.afcc.ru",
"callback":"qwerty"}
,{ "url":"http://kamexpert.ru",
"callback":"qwerty"}
,{ "url":"http://кам-услуги.рф",
"callback":"qwerty"}
,{ "url":"http://petropavlovsk-expertiza.ru",
"callback":"qwerty"}
,{ "url":"http://kapital.plus",
"callback":"qwerty"}
,{ "url":"http://dtp-help.ru",
"callback":"qwerty"}
,{ "url":"http://dtp-prof.ru",
"callback":"qwerty"}
,{ "url":"http://www.uralairlines.ru",
"callback":"qwerty"}
,{ "url":"http://www.elckam.ru",
"callback":"qwerty"}
,{ "url":"http://tst-cargo.ru",
"callback":"qwerty"}
,{ "url":"http://mts-ms.ru",
"callback":"qwerty"}
,{ "url":"http://gtdel.com",
"callback":"qwerty"}
,{ "url":"http://vostok-exp.ru",
"callback":"qwerty"}
,{ "url":"http://www.expeditor-pk.ru",
"callback":"qwerty"}
,{ "url":"http://dtservice.ru",
"callback":"qwerty"}
,{ "url":"http://glav-dostavka.ru",
"callback":"qwerty"}
,{ "url":"http://www.stk-express.ru",
"callback":"qwerty"}
,{ "url":"http://procargo.su",
"callback":"qwerty"}
,{ "url":"http://www.kans-kam.ru",
"callback":"qwerty"}
,{ "url":"http://promit.pro",
"callback":"qwerty"}
,{ "url":"http://www.cccb.ru",
"callback":"qwerty"}
,{ "url":"http://armada-cargo.ru",
"callback":"qwerty"}
,{ "url":"http://gorodskoy-kurier41rus.tt34.ru",
"callback":"qwerty"}
,{ "url":"http://tkcargo.su",
"callback":"qwerty"}
,{ "url":"http://mashandling.ru",
"callback":"qwerty"}
,{ "url":"http://airport-pkc.ru",
"callback":"qwerty"}
,{ "url":"http://tk-ankor.ru",
"callback":"qwerty"}
,{ "url":"http://www.cdek.ru",
"callback":"qwerty"}
,{ "url":"http://www.groupst.ru",
"callback":"qwerty"}
,{ "url":"http://vityaz-aero.ru",
"callback":"qwerty"}
,{ "url":"http://www.dhl.ru",
"callback":"qwerty"}
,{ "url":"http://www.ponyexpress.ru",
"callback":"qwerty"}
,{ "url":"http://spsr.ru",
"callback":"qwerty"}
,{ "url":"http://dpd.ru",
"callback":"qwerty"}
,{ "url":"http://pecom.ru",
"callback":"qwerty"}
,{ "url":"http://nrg-tk.ru",
"callback":"qwerty"}
,{ "url":"http://kskamchatka.ru",
"callback":"qwerty"}
,{ "url":"http://www.cse.ru",
"callback":"qwerty"}
,{ "url":"http://www.transintek.ru",
"callback":"qwerty"}
,{ "url":"http://masterfibre-kamchatka.ru",
"callback":"qwerty"}
,{ "url":"http://spbrealty.ru",
"callback":"qwerty"}
,{ "url":"http://lenspecsmu.ru",
"callback":"qwerty"}
,{ "url":"http://lsr.ru",
"callback":"qwerty"}
,{ "url":"http://стройдекор.сайт",
"callback":"qwerty"}
,{ "url":"http://akfa-u.ru",
"callback":"qwerty"}
,{ "url":"http://zod41.ru",
"callback":"qwerty"}
,{ "url":"http://svetlyi-dom-kamchatka.ru",
"callback":"qwerty"}
,{ "url":"http://www.sfera41.ru",
"callback":"qwerty"}
,{ "url":"http://energoresurs-m.tiu.ru",
"callback":"qwerty"}
,{ "url":"http://kam-elevator.ru",
"callback":"qwerty"}
,{ "url":"http://aleir-kam.ru",
"callback":"qwerty"}
,{ "url":"http://usas-stroy.ru",
"callback":"qwerty"}
,{ "url":"http://sdrs-pk.ru",
"callback":"qwerty"}
,{ "url":"http://ustoym.ru",
"callback":"qwerty"}
,{ "url":"http://www.kamenergo.ru",
"callback":"qwerty"}
,{ "url":"http://kilowatt-pk.ru",
"callback":"qwerty"}
,{ "url":"http://vienergy.ru",
"callback":"qwerty"}
,{ "url":"http://nanotrast.ru",
"callback":"qwerty"}
,{ "url":"http://www.rsdvr.ru",
"callback":"qwerty"}
,{ "url":"http://ecocitydv.ru",
"callback":"qwerty"}
,{ "url":"http://umitpk.ru",
"callback":"qwerty"}
,{ "url":"http://www.vizir41.ru",
"callback":"qwerty"}
,{ "url":"http://Temp41.ru",
"callback":"qwerty"}
,{ "url":"http://www.euro-line.org",
"callback":"qwerty"}
,{ "url":"http://kamdoors.ru",
"callback":"qwerty"}
,{ "url":"http://r41.rosinv.ru",
"callback":"qwerty"}
,{ "url":"http://кск-альянс.рф",
"callback":"qwerty"}
,{ "url":"http://www.ecopro100.ru",
"callback":"qwerty"}
,{ "url":"http://ooo-proekt-m.ru",
"callback":"qwerty"}
,{ "url":"http://www.evoks41.ru",
"callback":"qwerty"}
,{ "url":"http://www.ngorod.ru",
"callback":"qwerty"}
,{ "url":"http://kames41.ru",
"callback":"qwerty"}
,{ "url":"http://41kgp.ru",
"callback":"qwerty"}
,{ "url":"http://aqua-pro41.ru",
"callback":"qwerty"}
,{ "url":"http://www.emsd.ru",
"callback":"qwerty"}
,{ "url":"http://ciiskam41.ru",
"callback":"qwerty"}
,{ "url":"http://www.avers1.ru",
"callback":"qwerty"}
,{ "url":"http://topoburo.ru",
"callback":"qwerty"}
,{ "url":"http://pks41.ru",
"callback":"qwerty"}
,{ "url":"http://petropavlovsk.gruzcik.ru",
"callback":"qwerty"}
,{ "url":"http://poryadok41.ru | http://порядок41.рф",
"callback":"qwerty"}
,{ "url":"http://347700.ru",
"callback":"qwerty"}
,{ "url":"http://41sk.ru",
"callback":"qwerty"}
,{ "url":"http://torgovayatehnika.ru",
"callback":"qwerty"}
,{ "url":"http://Www.kamchattisiz.ru",
"callback":"qwerty"}
,{ "url":"http://isocork.ru | http://altermo.ru | http://hydroteks.ru",
"callback":"qwerty"}
,{ "url":"http://25pro.ru",
"callback":"qwerty"}
,{ "url":"http://nikolas41.ru",
"callback":"qwerty"}
,{ "url":"http://www.stek-kom.ru",
"callback":"qwerty"}
,{ "url":"http://www.malahit-kamen.ru",
"callback":"qwerty"}
,{ "url":"http://selhozservis2001.ru",
"callback":"qwerty"}
,{ "url":"http://engineer-teplotehnik-41.pulscen.ru",
"callback":"qwerty"}
,{ "url":"http://www.rosimport41.ru",
"callback":"qwerty"}
,{ "url":"http://magazin-avrora.ru",
"callback":"qwerty"}
,{ "url":"http://410089.ru",
"callback":"qwerty"}
,{ "url":"http://prom41.ru",
"callback":"qwerty"}
,{ "url":"http://зеленыйбор41.рф",
"callback":"qwerty"}
,{ "url":"http://nk-kamchatka.tiu.ru",
"callback":"qwerty"}
,{ "url":"http://perspektivakam.ru",
"callback":"qwerty"}
,{ "url":"http://profnastil.ipkam.ru",
"callback":"qwerty"}
,{ "url":"http://kamteplo.ru",
"callback":"qwerty"}
,{ "url":"http://www.tstn.biz",
"callback":"qwerty"}
,{ "url":"http://eurocerama.su",
"callback":"qwerty"}
,{ "url":"http://masterplus13.ru",
"callback":"qwerty"}
,{ "url":"http://kamchatka.pro",
"callback":"qwerty"}
,{ "url":"http://mirsan41.ru",
"callback":"qwerty"}
,{ "url":"http://www.stilteks.ru",
"callback":"qwerty"}
,{ "url":"http://kamvariant.ru",
"callback":"qwerty"}
,{ "url":"http://410089.ru",
"callback":"qwerty"}
,{ "url":"http://navigator41.ru",
"callback":"qwerty"}
,{ "url":"http://sk-kum.ru",
"callback":"qwerty"}
,{ "url":"http://karyer-kam.ru",
"callback":"qwerty"}
,{ "url":"http://www.ksm41.biz",
"callback":"qwerty"}
,{ "url":"http://молот41.рф",
"callback":"qwerty"}
,{ "url":"http://legionural.ru",
"callback":"qwerty"}
,{ "url":"http://камплит-камчатка.рф | http://петрович-смеси.рф",
"callback":"qwerty"}
,{ "url":"http://kamsystem.ru",
"callback":"qwerty"}
,{ "url":"http://newhome41.ru",
"callback":"qwerty"}
,{ "url":"http://snabkomplekt41.ru",
"callback":"qwerty"}
,{ "url":"http://ktp41.ru",
"callback":"qwerty"}
,{ "url":"http://www.ecostar-tech.ru",
"callback":"qwerty"}
,{ "url":"http://o2-41.ru",
"callback":"qwerty"}
,{ "url":"http://www.svarka-vl.com",
"callback":"qwerty"}
,{ "url":"http://pkkris.net",
"callback":"qwerty"}
,{ "url":"http://3dflow.ru",
"callback":"qwerty"}
,{ "url":"http://kamplastik.ru",
"callback":"qwerty"}
,{ "url":"http://bolars.ru | http://mascarade.ru",
"callback":"qwerty"}
,{ "url":"http://www.nsk41.com",
"callback":"qwerty"}
,{ "url":"http://gazprom-agnks.ru",
"callback":"qwerty"}
,{ "url":"http://mortrast.ru",
"callback":"qwerty"}
,{ "url":"http://www.otk41.ru",
"callback":"qwerty"}
,{ "url":"http://metall-arm.ru",
"callback":"qwerty"}
,{ "url":"http://primmetallsnab.ru",
"callback":"qwerty"}
,{ "url":"http://kamplazma.ru",
"callback":"qwerty"}
,{ "url":"http://www.kamchatka.spk.ru",
"callback":"qwerty"}
,{ "url":"http://antey-m.ru",
"callback":"qwerty"}
,{ "url":"http://kovka41.ru",
"callback":"qwerty"}
,{ "url":"http://stek-kom.ru",
"callback":"qwerty"}
,{ "url":"http://ratibor555.ru",
"callback":"qwerty"}
,{ "url":"http://www.antey-m.ru",
"callback":"qwerty"}
,{ "url":"http://www.ct-ru.com",
"callback":"qwerty"}
,{ "url":"http://gvozd41.ru",
"callback":"qwerty"}
,{ "url":"http://www.mk-27.ru",
"callback":"qwerty"}
,{ "url":"http://tvibo.ru",
"callback":"qwerty"}
,{ "url":"http://ru.zolotokamchatki.ru",
"callback":"qwerty"}
,{ "url":"http://zolotokamchatki.ru",
"callback":"qwerty"}
,{ "url":"http://guzhf.ru",
"callback":"qwerty"}
,{ "url":"http://www.kamgrad-servis.ru",
"callback":"qwerty"}
,{ "url":"http://avachadom.ru",
"callback":"qwerty"}
,{ "url":"http://pk-dom.ru",
"callback":"qwerty"}
,{ "url":"http://yk-aliance.ru",
"callback":"qwerty"}
,{ "url":"http://mig-gkh.ru",
"callback":"qwerty"}
,{ "url":"http://lider-yk.com",
"callback":"qwerty"}
,{ "url":"http://pkvoda.ru",
"callback":"qwerty"}
,{ "url":"http://ugkhpk.ru",
"callback":"qwerty"}
,{ "url":"http://at41.ru",
"callback":"qwerty"}
,{ "url":"http://grupsm.ru",
"callback":"qwerty"}
,{ "url":"http://www.spetstrans.com | http://spetstrans-kam.ru/",
"callback":"qwerty"}
,{ "url":"http://tyreplus.ru",
"callback":"qwerty"}
,{ "url":"http://retrofit-kam.ru",
"callback":"qwerty"}
,{ "url":"http://www.studiocar.me",
"callback":"qwerty"}
,{ "url":"http://avtovizit.ipkam.ru",
"callback":"qwerty"}
,{ "url":"http://avto-tema.com",
"callback":"qwerty"}
,{ "url":"http://kamreo.ru",
"callback":"qwerty"}
,{ "url":"http://www.avarkom41.ru",
"callback":"qwerty"}
,{ "url":"http://glonassgps.com",
"callback":"qwerty"}
,{ "url":"http://www.tahograf-41.ru",
"callback":"qwerty"}
,{ "url":"http://pos-pk.ru",
"callback":"qwerty"}
,{ "url":"http://sorokin.ru",
"callback":"qwerty"}
,{ "url":"http://box109.ru",
"callback":"qwerty"}
,{ "url":"http://www.studiocar.me",
"callback":"qwerty"}
,{ "url":"http://dalcar.ru",
"callback":"qwerty"}
,{ "url":"http://dalservis.com",
"callback":"qwerty"}
,{ "url":"http://uralmarka.ru",
"callback":"qwerty"}
,{ "url":"http://www.modernmachinery.ru",
"callback":"qwerty"}
,{ "url":"http://www.nsk41.com",
"callback":"qwerty"}
,{ "url":"http://mir-krasok41.ru",
"callback":"qwerty"}
,{ "url":"http://avtokraski41.ru",
"callback":"qwerty"}
,{ "url":"http://electronic-auto.ru",
"callback":"qwerty"}
,{ "url":"http://check41.ru",
"callback":"qwerty"}
,{ "url":"http://jem-garage.com",
"callback":"qwerty"}
,{ "url":"http://oktan41.ru",
"callback":"qwerty"}
,{ "url":"http://cto26km.ru",
"callback":"qwerty"}
,{ "url":"http://магистраль41.рф",
"callback":"qwerty"}
,{ "url":"http://avtomirpk.ru",
"callback":"qwerty"}
,{ "url":"http://www.prado-pk.ru",
"callback":"qwerty"}
,{ "url":"http://akkam.ru",
"callback":"qwerty"}
,{ "url":"http://stuffoil.ru",
"callback":"qwerty"}
,{ "url":"http://vnedrenie-vl.ru",
"callback":"qwerty"}
,{ "url":"http://kmv1.ru | http://ttdom41.ru",
"callback":"qwerty"}
,{ "url":"http://www.eastpole.ru",
"callback":"qwerty"}
,{ "url":"http://avtozvuk41.ru",
"callback":"qwerty"}
,{ "url":"http://lukoil.kws.ru",
"callback":"qwerty"}
,{ "url":"http://autodealer.fm",
"callback":"qwerty"}
,{ "url":"http://avto.nz",
"callback":"qwerty"}
,{ "url":"http://www.rzt41.ru",
"callback":"qwerty"}
,{ "url":"http://ati41.ru",
"callback":"qwerty"}
,{ "url":"http://www.avtomirpk.ru",
"callback":"qwerty"}
,{ "url":"http://mitsubishi-kam.ru",
"callback":"qwerty"}
,{ "url":"http://wstruck.ru | http://mazhab.ru",
"callback":"qwerty"}
,{ "url":"http://www.rzt41.ru",
"callback":"qwerty"}
,{ "url":"http://avtokam.azgaz.ru",
"callback":"qwerty"}
,{ "url":"http://zip41.ru",
"callback":"qwerty"}
,{ "url":"http://kamaz41.ru",
"callback":"qwerty"}
,{ "url":"http://rzt41.ru",
"callback":"qwerty"}
,{ "url":"http://урал-дизель.рф",
"callback":"qwerty"}
,{ "url":"http://espz.ru",
"callback":"qwerty"}
,{ "url":"http://www.ratepart.ru",
"callback":"qwerty"}
,{ "url":"http://truckdv.ru",
"callback":"qwerty"}
,{ "url":"http://central-alarm.ru",
"callback":"qwerty"}
,{ "url":"http://avtovizit.ipkam.ru",
"callback":"qwerty"}
,{ "url":"http://koonka.shop | http://avtogt.ru",
"callback":"qwerty"}
,{ "url":"http://www.farpost.ru/user/Badroadclub/",
"callback":"qwerty"}
,{ "url":"http://toyota41.ru",
"callback":"qwerty"}
,{ "url":"http://autoshik41.ru",
"callback":"qwerty"}
,{ "url":"http://avtokamchatka.ru",
"callback":"qwerty"}
,{ "url":"http://avtokamchatka.ru",
"callback":"qwerty"}
,{ "url":"http://evakuator41.ru",
"callback":"qwerty"}
,{ "url":"http://evakuator-kamchatka.ru",
"callback":"qwerty"}
,{ "url":"http://prokatavto001.umi.ru",
"callback":"qwerty"}
,{ "url":"http://taximaximapp.ru | http://www.taximaxim.com",
"callback":"qwerty"}
,{ "url":"http://lukoil-shop.ru",
"callback":"qwerty"}
,{ "url":"http://41kam.ru",
"callback":"qwerty"}
,{ "url":"http://portalmfc.kamgov.ru",
"callback":"qwerty"}
,{ "url":"http://kamchatkavr.wixsite.com/vr-pk",
"callback":"qwerty"}
,{ "url":"http://1cm.ru",
"callback":"qwerty"}
,{ "url":"http://kamchatka.shop.mts.ru/?utm_source=2gis&utm_medium=cpc&utm_campaign=ip-mts_2gis_%20Petropavlovsk-Kamchatsky&utm_term=%7Bkeyword%7D&utm_content=main",
"callback":"qwerty"}
,{ "url":"http://pochta.ru",
"callback":"qwerty"}
,{ "url":"http://aokap.ru",
"callback":"qwerty"}
,{ "url":"http://антошка20.рф",
"callback":"qwerty"}
,{ "url":"http://belochka37.ru",
"callback":"qwerty"}
,{ "url":"http://shkola-vgp.ru",
"callback":"qwerty"}
,{ "url":"http://veloengineer.ru",
"callback":"qwerty"}
,{ "url":"http://amto-hotel.ru",
"callback":"qwerty"}
,{ "url":"http://kamchatkasummer.ru | http://allaboutkamchatka.ru | http://kamchatkawinter.com",
"callback":"qwerty"}
,{ "url":"http://bustravel41.ru",
"callback":"qwerty"}
,{ "url":"http://ru.go2kamchatka.com",
"callback":"qwerty"}
,{ "url":"http://ru.go2kamchatka.com",
"callback":"qwerty"}
,{ "url":"http://spetchteh41.ru",
"callback":"qwerty"}
,{ "url":"http://www.evrochehol.ru",
"callback":"qwerty"}
,{ "url":"http://profitbank.ru",
"callback":"qwerty"}
,{ "url":"http://vzmfo.ru",
"callback":"qwerty"}
,{ "url":"http://tab-eks.ru",
"callback":"qwerty"}
,{ "url":"http://salmonica.ru",
"callback":"qwerty"}
,{ "url":"http://mormer.ru",
"callback":"qwerty"}
,{ "url":"http://fishpolaris.ru",
"callback":"qwerty"}
,{ "url":"http://www.llflot.ru",
"callback":"qwerty"}
,{ "url":"http://bekerev.ru",
"callback":"qwerty"}
,{ "url":"http://okeanrybflot.ru",
"callback":"qwerty"}
,{ "url":"http://www.svoyapaseka.ru",
"callback":"qwerty"}
,{ "url":"http://www.agrotek.ru",
"callback":"qwerty"}
,{ "url":"http://apukinskoe.ru",
"callback":"qwerty"}
,{ "url":"http://33pingvina.ru",
"callback":"qwerty"}
,{ "url":"http://molkam.ru",
"callback":"qwerty"}
,{ "url":"http://pivmania.ru",
"callback":"qwerty"}
,{ "url":"http://kampivo.ru",
"callback":"qwerty"}
,{ "url":"http://avachinskoe.ru",
"callback":"qwerty"}
,{ "url":"http://kamparni.ru",
"callback":"qwerty"}
,{ "url":"http://master-tort.com",
"callback":"qwerty"}
,{ "url":"http://tort41.ru",
"callback":"qwerty"}
,{ "url":"http://kamhleb.ru",
"callback":"qwerty"}
,{ "url":"http://agrotek.ru",
"callback":"qwerty"}
,{ "url":"http://roll-express.com",
"callback":"qwerty"}
,{ "url":"http://фридом.рф",
"callback":"qwerty"}
,{ "url":"http://medzhelch.ru",
"callback":"qwerty"}
,{ "url":"http://kamchatprod.ru",
"callback":"qwerty"}
,{ "url":"http://aquavulcanos.com",
"callback":"qwerty"}
,{ "url":"http://www.pivopk.ru",
"callback":"qwerty"}
,{ "url":"http://www.pivopk.ru",
"callback":"qwerty"}
,{ "url":"http://kampivo.ru",
"callback":"qwerty"}
,{ "url":"http://malki.ru",
"callback":"qwerty"}
,{ "url":"http://www.орлан41.рф",
"callback":"qwerty"}
,{ "url":"http://mgroup41.ru",
"callback":"qwerty"}
,{ "url":"http://rosinkas.ru",
"callback":"qwerty"}
,{ "url":"http://avanpost.ds41.ru",
"callback":"qwerty"}
,{ "url":"http://kadalit.ru",
"callback":"qwerty"}
,{ "url":"http://www.st-remservice.ru/",
"callback":"qwerty"}
,{ "url":"http://www.zpo-obereg.ru",
"callback":"qwerty"}
,{ "url":"http://www.videozorro.ru",
"callback":"qwerty"}
,{ "url":"http://newton41.ru",
"callback":"qwerty"}
,{ "url":"http://integral-sb.ru",
"callback":"qwerty"}
,{ "url":"http://фёст.рф",
"callback":"qwerty"}
,{ "url":"http://fire-audit.su",
"callback":"qwerty"}
,{ "url":"http://kadalit.ru",
"callback":"qwerty"}
,{ "url":"http://кск-альянс.рф",
"callback":"qwerty"}
,{ "url":"http://school-pk.ru",
"callback":"qwerty"}
,{ "url":"http://alphasecurity.ru",
"callback":"qwerty"}
,{ "url":"http://teko.ds41.ru",
"callback":"qwerty"}
,{ "url":"http://www.kamzamok.ru",
"callback":"qwerty"}
,{ "url":"http://rosgvard.ru",
"callback":"qwerty"}
,{ "url":"http://ледимама.рф",
"callback":"qwerty"}
,{ "url":"http://www.lasmamas.ru",
"callback":"qwerty"}
,{ "url":"http://nagrada41.ru",
"callback":"qwerty"}
,{ "url":"http://mebus-shoes.ru",
"callback":"qwerty"}
,{ "url":"http://сцена-камчатка.рф",
"callback":"qwerty"}
,{ "url":"http://kamuflag-kamchatka.com",
"callback":"qwerty"}
,{ "url":"http://спецодежда.рф",
"callback":"qwerty"}
,{ "url":"http://kurtkamoda.ru",
"callback":"qwerty"}
,{ "url":"http://www.ralf.ru | http://www.ralf.ru",
"callback":"qwerty"}
,{ "url":"http://www.ecco-shoes.ru",
"callback":"qwerty"}
,{ "url":"http://tervolina.ru",
"callback":"qwerty"}
,{ "url":"http://www.aptrade.ru",
"callback":"qwerty"}
,{ "url":"http://palmetta.ru",
"callback":"qwerty"}
,{ "url":"http://milavitsa.ru",
"callback":"qwerty"}
,{ "url":"http://calzedonia.com",
"callback":"qwerty"}
,{ "url":"http://viluchinsk.su",
"callback":"qwerty"}
,{ "url":"http://www.novkniga.ru",
"callback":"qwerty"}
,{ "url":"http://www.novkniga.ru",
"callback":"qwerty"}
,{ "url":"http://www.novkniga.ru",
"callback":"qwerty"}
,{ "url":"http://www.novkniga.ru",
"callback":"qwerty"}
,{ "url":"http://butik-bezgranic.ru",
"callback":"qwerty"}
,{ "url":"http://www.ostin.com",
"callback":"qwerty"}
,{ "url":"http://elis.ru",
"callback":"qwerty"}
,{ "url":"http://www.korea-street.ru",
"callback":"qwerty"}
,{ "url":"http://loverepublic.ru/",
"callback":"qwerty"}
,{ "url":"http://www.befree.ru",
"callback":"qwerty"}
,{ "url":"http://zolla.ru",
"callback":"qwerty"}
,{ "url":"http://www.westland.ru",
"callback":"qwerty"}
,{ "url":"http://ptenec-kamchatka.ru",
"callback":"qwerty"}
,{ "url":"http://hb-detkam.ru",
"callback":"qwerty"}
,{ "url":"http://www.kolosok41.ru",
"callback":"qwerty"}
,{ "url":"http://www.emae.ru",
"callback":"qwerty"}
,{ "url":"http://умка41.рф",
"callback":"qwerty"}
,{ "url":"http://www.boobl-goom.ru",
"callback":"qwerty"}
,{ "url":"http://quiksilver.ru",
"callback":"qwerty"}
,{ "url":"http://www.gloria-jeans.ru",
"callback":"qwerty"}
,{ "url":"http://stilnyashka.com",
"callback":"qwerty"}
,{ "url":"http://www.orby.ru",
"callback":"qwerty"}
,{ "url":"http://www.gulliver-wear.ru",
"callback":"qwerty"}
,{ "url":"http://www.21shop.ru",
"callback":"qwerty"}
,{ "url":"http://youthstore.ru",
"callback":"qwerty"}
,{ "url":"http://www.westfalika.ru",
"callback":"qwerty"}
,{ "url":"http://www.donatto.ru",
"callback":"qwerty"}
,{ "url":"http://www.dcrussia.ru",
"callback":"qwerty"}
,{ "url":"http://www.kari.com",
"callback":"qwerty"}
,{ "url":"http://www.ladycollection.com",
"callback":"qwerty"}
,{ "url":"http://www.swarovski.com",
"callback":"qwerty"}
,{ "url":"http://e4u-41.ru",
"callback":"qwerty"}
,{ "url":"http://babelfish.pro",
"callback":"qwerty"}
,{ "url":"http://kamsan41.ru",
"callback":"qwerty"}
,{ "url":"http://kamch-internat.ucoz.ru",
"callback":"qwerty"}
,{ "url":"http://kamkrai-shkola1.ru",
"callback":"qwerty"}
,{ "url":"http://nik-shkola.org.ru",
"callback":"qwerty"}
,{ "url":"http://vecherka-elizovo.ru",
"callback":"qwerty"}
,{ "url":"http://vschool13pkgo.edusite.ru",
"callback":"qwerty"}
,{ "url":"http://schoolsad5.ru",
"callback":"qwerty"}
,{ "url":"http://termschool.ru",
"callback":"qwerty"}
,{ "url":"http://ksosh-r41.ucoz.ru",
"callback":"qwerty"}
,{ "url":"http://nagorschool.ucoz.ru",
"callback":"qwerty"}
,{ "url":"http://www.razdol-shkola.ru",
"callback":"qwerty"}
,{ "url":"http://school2vil.ucoz.ru",
"callback":"qwerty"}
,{ "url":"http://schoolpioner.ucoz.ru",
"callback":"qwerty"}
,{ "url":"http://edu.pkgo.ru/education/school/ou37",
"callback":"qwerty"}
,{ "url":"http://vschool16.ucoz.org",
"callback":"qwerty"}
,{ "url":"http://vilschool9.ucoz.ru",
"callback":"qwerty"}
,{ "url":"http://school2-el.ucoz.ru",
"callback":"qwerty"}
,{ "url":"http://school3kam.ucoz.ru",
"callback":"qwerty"}
,{ "url":"http://kamschool41.ru",
"callback":"qwerty"}
,{ "url":"http://vilschool1.ru",
"callback":"qwerty"}
,{ "url":"http://el-school9.ru",
"callback":"qwerty"}
,{ "url":"http://lomonosov-school.ru",
"callback":"qwerty"}
,{ "url":"http://school6pkgo.ucoz.net",
"callback":"qwerty"}
,{ "url":"http://17школа.рф",
"callback":"qwerty"}
,{ "url":"http://school12-pkgo.ucoz.ru",
"callback":"qwerty"}
,{ "url":"http://school5pkgo.ucoz.ru",
"callback":"qwerty"}
,{ "url":"http://school9pk.ucoz.ru",
"callback":"qwerty"}
,{ "url":"http://мбоусош7.рф",
"callback":"qwerty"}
,{ "url":"http://school8-el.ucoz.ru",
"callback":"qwerty"}
,{ "url":"http://school20pk.org.ru",
"callback":"qwerty"}
,{ "url":"http://school2-pk.ucoz.ru",
"callback":"qwerty"}
,{ "url":"http://www.ш32.рф",
"callback":"qwerty"}
,{ "url":"http://school35pkgo.edusite.ru",
"callback":"qwerty"}
,{ "url":"http://school-10-pkgo.ucoz.ru",
"callback":"qwerty"}
,{ "url":"http://school3-pushkin.ucoz.ru",
"callback":"qwerty"}
,{ "url":"http://школа15пк.рф",
"callback":"qwerty"}
,{ "url":"http://shkola4pk.ucoz.ru",
"callback":"qwerty"}
,{ "url":"http://school24-pkgo.ucoz.ru",
"callback":"qwerty"}
,{ "url":"http://pk-school26.ucoz.ru",
"callback":"qwerty"}
,{ "url":"http://school45.ru",
"callback":"qwerty"}
,{ "url":"http://school8pk.ru",
"callback":"qwerty"}
,{ "url":"http://school1.pkgo.ru",
"callback":"qwerty"}
,{ "url":"http://kam36.edusite.ru",
"callback":"qwerty"}
,{ "url":"http://school43pk.ru",
"callback":"qwerty"}
,{ "url":"http://eduold.pkgo.ru/education/school/ou11/",
"callback":"qwerty"}
,{ "url":"http://school40-pk.ucoz.ru",
"callback":"qwerty"}
,{ "url":"http://school28-pk.ucoz.ru",
"callback":"qwerty"}
,{ "url":"http://school33pk.ru",
"callback":"qwerty"}
,{ "url":"http://school30pkgo.ru",
"callback":"qwerty"}
,{ "url":"http://school34.ipkam.ru",
"callback":"qwerty"}
,{ "url":"http://school31pkgo.ru",
"callback":"qwerty"}
,{ "url":"http://school7pkgo41.ru",
"callback":"qwerty"}
,{ "url":"http://school27kam.ru",
"callback":"qwerty"}
,{ "url":"http://school42pkgo41.ucoz.ru",
"callback":"qwerty"}
,{ "url":"http://teremok-kam.ru",
"callback":"qwerty"}
,{ "url":"http://karuselpk.ru",
"callback":"qwerty"}
,{ "url":"http://city-pages.info/stupeni",
"callback":"qwerty"}
,{ "url":"http://www.montessori41.ru",
"callback":"qwerty"}
,{ "url":"http://www.montessori-pk.ru",
"callback":"qwerty"}
,{ "url":"http://evrika41.ru",
"callback":"qwerty"}
,{ "url":"http://matreshkapk.wordpress.com/",
"callback":"qwerty"}
,{ "url":"http://kamchatgtu.ru",
"callback":"qwerty"}
,{ "url":"http://kamchatgtu.ru | http://www.kamchatgtu.ru/fey/about/default.aspx",
"callback":"qwerty"}
,{ "url":"http://www.kamgu.ru",
"callback":"qwerty"}
,{ "url":"http://kamchatgtu.ru | http://www.kamchatgtu.ru/morfak/ofak/default.aspx",
"callback":"qwerty"}
,{ "url":"http://kamchatgtu.ru | http://kamchatgtu.ru/techfak/about/default.aspx",
"callback":"qwerty"}
,{ "url":"http://kamchatgtu.ru | http://www.kamchatgtu.ru/kolledzh/default.aspx",
"callback":"qwerty"}
,{ "url":"http://www.sde.ru",
"callback":"qwerty"}
,{ "url":"http://izdo.vvsu.ru",
"callback":"qwerty"}
,{ "url":"http://pk.ruc.su",
"callback":"qwerty"}
,{ "url":"http://kamchatgtu.ru | http://kamchatgtu.ru/fit/about/default.aspx",
"callback":"qwerty"}
,{ "url":"http://kpt-kamchatka.ru",
"callback":"qwerty"}
,{ "url":"http://www.kptelz.ru/",
"callback":"qwerty"}
,{ "url":"http://vil-kit.ru",
"callback":"qwerty"}
,{ "url":"http://www.sosnovka.kov-obr.ru",
"callback":"qwerty"}
,{ "url":"http://www.kammt.ru",
"callback":"qwerty"}
,{ "url":"http://www.koop41.ru",
"callback":"qwerty"}
,{ "url":"http://umckam.ru",
"callback":"qwerty"}
,{ "url":"http://камэкспертиза.рф",
"callback":"qwerty"}
,{ "url":"http://камукк.рф",
"callback":"qwerty"}
,{ "url":"http://www.krumc.ru",
"callback":"qwerty"}
,{ "url":"http://iq007-school.ru",
"callback":"qwerty"}
,{ "url":"http://medvedschool.com",
"callback":"qwerty"}
,{ "url":"http://erudit-kam.ru",
"callback":"qwerty"}
,{ "url":"http://ucmasru.com",
"callback":"qwerty"}
,{ "url":"http://www.studkam41.ru",
"callback":"qwerty"}
,{ "url":"http://center-kam.ru",
"callback":"qwerty"}
,{ "url":"http://Kampb.ru",
"callback":"qwerty"}
,{ "url":"http://www.atonot.ru",
"callback":"qwerty"}
,{ "url":"http://www.kamfs.ru",
"callback":"qwerty"}
,{ "url":"http://www.kamcot.ru",
"callback":"qwerty"}
,{ "url":"http://www.kamstorm.ru",
"callback":"qwerty"}
,{ "url":"http://okeanrybflot.ru",
"callback":"qwerty"}
,{ "url":"http://jschool-pk.org",
"callback":"qwerty"}
,{ "url":"http://studinter.ru",
"callback":"qwerty"}
,{ "url":"http://edu.pkgo.ru/education/children/ds52",
"callback":"qwerty"}
,{ "url":"http://www.kamniro.ru",
"callback":"qwerty"}
,{ "url":"http://febras.ru",
"callback":"qwerty"}
,{ "url":"http://emsd.ru",
"callback":"qwerty"}
,{ "url":"http://www.emsd.ru",
"callback":"qwerty"}
,{ "url":"http://www.ikir.ru",
"callback":"qwerty"}
,{ "url":"http://kamstat.gks.ru",
"callback":"qwerty"}
,{ "url":"http://www.nigtc.ru",
"callback":"qwerty"}
,{ "url":"http://pozitiv41.ru",
"callback":"qwerty"}
,{ "url":"http://kamliceum.ucoz.ru",
"callback":"qwerty"}
,{ "url":"http://liceum46.edusite.ru",
"callback":"qwerty"}
,{ "url":"http://kamlib.ru",
"callback":"qwerty"}
,{ "url":"http://каммедколледж.рф",
"callback":"qwerty"}
,{ "url":"http://artpk.net",
"callback":"qwerty"}
,{ "url":"http://kamcollege.ru",
"callback":"qwerty"}
,{ "url":"http://prof41.ru",
"callback":"qwerty"}
,{ "url":"http://proficit41.ru",
"callback":"qwerty"}
,{ "url":"http://pk.ranepa.ru",
"callback":"qwerty"}
,{ "url":"http://art-school.kam.muzkult.ru",
"callback":"qwerty"}
,{ "url":"http://edhsh.kamch.muzkult.ru",
"callback":"qwerty"}
,{ "url":"http://lastochka1.ru",
"callback":"qwerty"}
,{ "url":"http://26-rosinka.ru",
"callback":"qwerty"}
,{ "url":"http://27-pochemuchka.ru",
"callback":"qwerty"}
,{ "url":"http://vasile.ucoz.ru",
"callback":"qwerty"}
,{ "url":"http://edu.pkgo.ru/education/children/ds36",
"callback":"qwerty"}
,{ "url":"http://edu.pkgo.ru/education/children/ds18",
"callback":"qwerty"}
,{ "url":"http://vildetsad3.ru",
"callback":"qwerty"}
,{ "url":"http://madou-17-41.ru",
"callback":"qwerty"}
,{ "url":"http://dou9star.ru",
"callback":"qwerty"}
,{ "url":"http://zhemchuzhinka20.ucoz.ru",
"callback":"qwerty"}
,{ "url":"http://edu.pkgo.ru/education/children/ds35",
"callback":"qwerty"}
,{ "url":"http://edu.pkgo.ru/education/children/ds12",
"callback":"qwerty"}
,{ "url":"http://mbdou-72-41.ru/ | http://edu.pkgo.ru/education/children/ds72",
"callback":"qwerty"}
,{ "url":"http://mbdou-09-41.ru",
"callback":"qwerty"}
,{ "url":"http://skazka14.ru",
"callback":"qwerty"}
,{ "url":"http://edu.pkgo.ru/education/children/ds24",
"callback":"qwerty"}
,{ "url":"http://4.41.ds.3535.ru",
"callback":"qwerty"}
,{ "url":"http://edu.pkgo.ru/education/children/ds26",
"callback":"qwerty"}
,{ "url":"http://edu.pkgo.ru/education/children/ds38",
"callback":"qwerty"}
,{ "url":"http://kolokolchik5.ucoz.ru",
"callback":"qwerty"}
,{ "url":"http://detsadik20.ucoz.ru",
"callback":"qwerty"}
,{ "url":"http://веселинка22.рф",
"callback":"qwerty"}
,{ "url":"http://mbdou-19-41.ru",
"callback":"qwerty"}
,{ "url":"http://mbdou-40-41.ru",
"callback":"qwerty"}
,{ "url":"http://edu.pkgo.ru/education/children/ds51",
"callback":"qwerty"}
,{ "url":"http://mbdou-10-41.ru",
"callback":"qwerty"}
,{ "url":"http://kamdetsad1.ru",
"callback":"qwerty"}
,{ "url":"http://ds15pk.ucoz.ru",
"callback":"qwerty"}
,{ "url":"http://mbdou-44-41.ru",
"callback":"qwerty"}
,{ "url":"http://kamdetsad-56.ru",
"callback":"qwerty"}
,{ "url":"http://mbdou-63-41.ru",
"callback":"qwerty"}
,{ "url":"http://edu.pkgo.ru/education/children/ds37",
"callback":"qwerty"}
,{ "url":"http://pkds31.ru",
"callback":"qwerty"}
,{ "url":"http://edu.pkgo.ru/education/children/ds53",
"callback":"qwerty"}
,{ "url":"http://madou-70-41.ru",
"callback":"qwerty"}
,{ "url":"http://detsad45.ru",
"callback":"qwerty"}
,{ "url":"http://pkds58.ru | http://edu.pkgo.ru/education/children/ds58",
"callback":"qwerty"}
,{ "url":"http://pkds57.ru",
"callback":"qwerty"}
,{ "url":"http://pkds22.ru",
"callback":"qwerty"}
,{ "url":"http://pkds28.ru",
"callback":"qwerty"}
,{ "url":"http://kamdetsad-42.ru",
"callback":"qwerty"}
,{ "url":"http://pkds6.ru",
"callback":"qwerty"}
,{ "url":"http://северяночка.рф",
"callback":"qwerty"}
,{ "url":"http://madou-39-41.ru",
"callback":"qwerty"}
,{ "url":"http://edu.pkgo.ru/education/children/ds48",
"callback":"qwerty"}
,{ "url":"http://edu.pkgo.ru/education/children/ds50",
"callback":"qwerty"}
,{ "url":"http://pkds41.ru",
"callback":"qwerty"}
,{ "url":"http://edu.pkgo.ru/education/children/ds11",
"callback":"qwerty"}
,{ "url":"http://pkdetsad43.ru",
"callback":"qwerty"}
,{ "url":"http://nikoldshi.ucoz.net",
"callback":"qwerty"}
,{ "url":"http://www.elizovodmsh.ru",
"callback":"qwerty"}
,{ "url":"http://музшкола1.рф",
"callback":"qwerty"}
,{ "url":"http://maudo-dms6.ru",
"callback":"qwerty"}
,{ "url":"http://piccolo3p-k.ucoz.ru | http://all.culture.ru",
"callback":"qwerty"}
,{ "url":"http://gim39.ucoz.ru",
"callback":"qwerty"}
,{ "url":"http://aplgo.com",
"callback":"qwerty"}
,{ "url":"http://kamchatkalink.wixsite.com/link",
"callback":"qwerty"}
,{ "url":"http://www.finam.ru",
"callback":"qwerty"}
,{ "url":"http://logospk.ru",
"callback":"qwerty"}
,{ "url":"http://центрподдержки.рф",
"callback":"qwerty"}
,{ "url":"http://muh.ru",
"callback":"qwerty"}
,{ "url":"http://www.dvf-vavt.ru",
"callback":"qwerty"}
,{ "url":"http://avtoluks41.ru",
"callback":"qwerty"}
,{ "url":"http://academy41.ru",
"callback":"qwerty"}
,{ "url":"http://www.kptelz.ru/",
"callback":"qwerty"}
,{ "url":"http://petravto.ru",
"callback":"qwerty"}
,{ "url":"http://olimp41rus.ru",
"callback":"qwerty"}
,{ "url":"http://авто-драйв41.рф",
"callback":"qwerty"}
,{ "url":"http://autodosaaf41.ru",
"callback":"qwerty"}
,{ "url":"http://avtoshkola41rus.ru",
"callback":"qwerty"}
,{ "url":"http://energoresurs-m.tiu.ru",
"callback":"qwerty"}
,{ "url":"http://www.petropavlovsk.irbispro.ru",
"callback":"qwerty"}
,{ "url":"http://kamfreon.ru",
"callback":"qwerty"}
,{ "url":"http://kamholod.ru",
"callback":"qwerty"}
,{ "url":"http://nikko-ru.com",
"callback":"qwerty"}
,{ "url":"http://sdv41.ru",
"callback":"qwerty"}
,{ "url":"http://oikos-kam.ru",
"callback":"qwerty"}
,{ "url":"http://russkiyles.ru/",
"callback":"qwerty"}
,{ "url":"http://azbukatentov.ru | http://geo-grid.ru",
"callback":"qwerty"}
,{ "url":"http://petipa.ru",
"callback":"qwerty"}
,{ "url":"http://kamexpert.ru",
"callback":"qwerty"}
,{ "url":"http://tech-a.pro",
"callback":"qwerty"}
,{ "url":"http://boreykam.ru",
"callback":"qwerty"}
,{ "url":"http://volt41.com",
"callback":"qwerty"}
,{ "url":"http://kvartal-center.ru",
"callback":"qwerty"}
,{ "url":"http://kam-kardio.ru",
"callback":"qwerty"}
,{ "url":"http://med.kamchatka.ru",
"callback":"qwerty"}
,{ "url":"http://vitauct.ru",
"callback":"qwerty"}
,{ "url":"http://psykamchatka.ru",
"callback":"qwerty"}
,{ "url":"http://psykamchatka.ucoz.ru",
"callback":"qwerty"}
,{ "url":"http://city-pages.info/woman-club",
"callback":"qwerty"}
,{ "url":"http://vernal-travel.ru",
"callback":"qwerty"}
,{ "url":"http://www.goldsgym.ru",
"callback":"qwerty"}
,{ "url":"http://www.logos41.ru",
"callback":"qwerty"}
,{ "url":"http://www.umkapk.ru",
"callback":"qwerty"}
,{ "url":"http://www.afrodita-centr.ru",
"callback":"qwerty"}
,{ "url":"http://mediteks.ru",
"callback":"qwerty"}
,{ "url":"http://brunovamakeup.ru",
"callback":"qwerty"}
,{ "url":"http://www.imenie-berezka.ru",
"callback":"qwerty"}
,{ "url":"http://rassvet41.ru",
"callback":"qwerty"}
,{ "url":"http://www.solnechnay.ru",
"callback":"qwerty"}
,{ "url":"http://www.hotelgelios.com",
"callback":"qwerty"}
,{ "url":"http://koster-kamchatka.ru",
"callback":"qwerty"}
,{ "url":"http://lespolyanakam.ru",
"callback":"qwerty"}
,{ "url":"http://www.titanpk.ru",
"callback":"qwerty"}
,{ "url":"http://kamsportpit.ru | http://reforma-kam.ru",
"callback":"qwerty"}
,{ "url":"http://nikadent-kam.ru",
"callback":"qwerty"}
,{ "url":"http://stomatologyaavangard.ru",
"callback":"qwerty"}
,{ "url":"http://kamchatka.smilerooms.ru",
"callback":"qwerty"}
,{ "url":"http://лора-дент.рф",
"callback":"qwerty"}
,{ "url":"http://www.unag-k.ru",
"callback":"qwerty"}
,{ "url":"http://www.kamdoctor.ru",
"callback":"qwerty"}
,{ "url":"http://dentaleks41.ru",
"callback":"qwerty"}
,{ "url":"http://siluetstom.ru",
"callback":"qwerty"}
,{ "url":"http://denta41.ru",
"callback":"qwerty"}
,{ "url":"http://www.zdorovie-kam.ru",
"callback":"qwerty"}
,{ "url":"http://www.dentes.ipkam.ru",
"callback":"qwerty"}
,{ "url":"http://kskpk.ru",
"callback":"qwerty"}
,{ "url":"http://ooo-denta-art.ru",
"callback":"qwerty"}
,{ "url":"http://dents-plus.com",
"callback":"qwerty"}
,{ "url":"http://vitadent41.ru",
"callback":"qwerty"}
,{ "url":"http://evrodent41.ru",
"callback":"qwerty"}
,{ "url":"http://dents-plus.com",
"callback":"qwerty"}
,{ "url":"http://www.pkgsp.ru",
"callback":"qwerty"}
,{ "url":"http://yadonor.ru/kamchatka",
"callback":"qwerty"}
,{ "url":"http://чиаус.рф",
"callback":"qwerty"}
,{ "url":"http://www.fbuz41.ru",
"callback":"qwerty"}
,{ "url":"http://жемчужина-камчатки.рус",
"callback":"qwerty"}
,{ "url":"http://groddom1.ru",
"callback":"qwerty"}
,{ "url":"http://домветеранов.рф",
"callback":"qwerty"}
,{ "url":"http://самокод.рф",
"callback":"qwerty"}
,{ "url":"http://barbershop_ntv",
"callback":"qwerty"}
,{ "url":"http://салонмария.рф",
"callback":"qwerty"}
,{ "url":"http://www.eyekraft.ru",
"callback":"qwerty"}
,{ "url":"http://www.luxoptica.pro",
"callback":"qwerty"}
,{ "url":"http://www.jekky.ru",
"callback":"qwerty"}
,{ "url":"http://eva-victoria.ru",
"callback":"qwerty"}
,{ "url":"http://sun41.ru",
"callback":"qwerty"}
,{ "url":"http://cirulnik.com",
"callback":"qwerty"}
,{ "url":"http://www.well-style.ru",
"callback":"qwerty"}
,{ "url":"http://www.salonya.su",
"callback":"qwerty"}
,{ "url":"http://stopa41.ru",
"callback":"qwerty"}
,{ "url":"http://cgb-viluchinsk.ru",
"callback":"qwerty"}
,{ "url":"http://med-inova.ru",
"callback":"qwerty"}
,{ "url":"http://kamnk.ru",
"callback":"qwerty"}
,{ "url":"http://t-zrenia.ru",
"callback":"qwerty"}
,{ "url":"http://www.medtechkam.ru",
"callback":"qwerty"}
,{ "url":"http://www.delrus.ru",
"callback":"qwerty"}
,{ "url":"http://www.addikt.ru",
"callback":"qwerty"}
,{ "url":"http://medunite.ru",
"callback":"qwerty"}
,{ "url":"http://dobrota.ru",
"callback":"qwerty"}
,{ "url":"http://www.radugazvukov.ru",
"callback":"qwerty"}
,{ "url":"http://avtomedcenter.su",
"callback":"qwerty"}
,{ "url":"http://esteticpkc.ru",
"callback":"qwerty"}
,{ "url":"http://invitro.ru",
"callback":"qwerty"}
,{ "url":"http://мсч.41.мвд.рф",
"callback":"qwerty"}
,{ "url":"http://kamfarma.ru",
"callback":"qwerty"}
,{ "url":"http://pmir41.ru",
"callback":"qwerty"}
,{ "url":"http://emi-school.ru",
"callback":"qwerty"}
,{ "url":"http://anvitashop.ru",
"callback":"qwerty"}
,{ "url":"http://letu.ru",
"callback":"qwerty"}
,{ "url":"http://marykay.ru",
"callback":"qwerty"}
,{ "url":"http://gloryon.com",
"callback":"qwerty"}
,{ "url":"http://www.meitan.ru",
"callback":"qwerty"}
,{ "url":"http://www.marykay.ru",
"callback":"qwerty"}
,{ "url":"http://rivegauche.ru",
"callback":"qwerty"}
,{ "url":"http://cosmetic-professional.ru",
"callback":"qwerty"}
,{ "url":"http://ru.oriflame.com",
"callback":"qwerty"}
,{ "url":"http://www.loccitane.ru",
"callback":"qwerty"}
,{ "url":"http://yubl.ru",
"callback":"qwerty"}
,{ "url":"http://clubxkam.ru",
"callback":"qwerty"}
,{ "url":"http://kam-linz.mcdir.ru",
"callback":"qwerty"}
,{ "url":"http://slimclub.ru",
"callback":"qwerty"}
,{ "url":"http://www.kam-kardio.ru",
"callback":"qwerty"}
,{ "url":"http://kkpnd.ru",
"callback":"qwerty"}
,{ "url":"http://unilab.su",
"callback":"qwerty"}
,{ "url":"http://www.uzi-vita.org",
"callback":"qwerty"}
,{ "url":"http://andromed-pk.ru",
"callback":"qwerty"}
,{ "url":"http://kamchatkagynecologicalclinic.ru",
"callback":"qwerty"}
,{ "url":"http://mrt-lider.ru/Petropavlovsk-Kamchatsky/",
"callback":"qwerty"}
,{ "url":"http://мцрадужный.рф",
"callback":"qwerty"}
,{ "url":"http://www.lacrimakamchatka.ru",
"callback":"qwerty"}
,{ "url":"http://medline41.ru",
"callback":"qwerty"}
,{ "url":"http://kamdoc.ru",
"callback":"qwerty"}
,{ "url":"http://mediteks.ru",
"callback":"qwerty"}
,{ "url":"http://www.gdp1pk.ru",
"callback":"qwerty"}
,{ "url":"http://pkgb2.ru",
"callback":"qwerty"}
,{ "url":"http://mse-kam.ru",
"callback":"qwerty"}
,{ "url":"http://www.kam-hospital.ru",
"callback":"qwerty"}
,{ "url":"http://pkgb2.ru",
"callback":"qwerty"}
,{ "url":"http://guz-kkdb.ru",
"callback":"qwerty"}
,{ "url":"http://www.dvomc41.ru",
"callback":"qwerty"}
,{ "url":"http://pkgb1.ru",
"callback":"qwerty"}
,{ "url":"http://artlife-kamchatka.ru",
"callback":"qwerty"}
,{ "url":"http://liwest.ru",
"callback":"qwerty"}
,{ "url":"http://siberianhealth.com",
"callback":"qwerty"}
,{ "url":"http://herbalife.ru",
"callback":"qwerty"}
,{ "url":"http://madhead.pro",
"callback":"qwerty"}
,{ "url":"http://oldboybarbershop.com",
"callback":"qwerty"}
,{ "url":"http://apteka-raduga.ru",
"callback":"qwerty"}
,{ "url":"http://www.minicen.ru",
"callback":"qwerty"}
,{ "url":"http://zdravcity.ru",
"callback":"qwerty"}
,{ "url":"http://aptekavega.ru",
"callback":"qwerty"}
,{ "url":"http://estet-kam.ru",
"callback":"qwerty"}
,{ "url":"http://www.kamspasalon.ru",
"callback":"qwerty"}
,{ "url":"http://strong41.ru",
"callback":"qwerty"}
,{ "url":"http://ormediumpk.ru",
"callback":"qwerty"}
,{ "url":"http://www.exclusivest.ru",
"callback":"qwerty"}
,{ "url":"http://vash-den.com",
"callback":"qwerty"}
,{ "url":"http://www.pushe.ru",
"callback":"qwerty"}
,{ "url":"http://expopk.ru",
"callback":"qwerty"}
,{ "url":"http://кухни41.рф",
"callback":"qwerty"}
,{ "url":"http://vip-art.ucoz.ru",
"callback":"qwerty"}
,{ "url":"http://sofiadoors.com",
"callback":"qwerty"}
,{ "url":"http://narod-kuhni.ru",
"callback":"qwerty"}
,{ "url":"http://ideakam.umi.ru",
"callback":"qwerty"}
,{ "url":"http://teploe-more.com",
"callback":"qwerty"}
,{ "url":"http://arsenalmebel.com",
"callback":"qwerty"}
,{ "url":"http://ortom.ru",
"callback":"qwerty"}
,{ "url":"http://tmf.tomsk.ru",
"callback":"qwerty"}
,{ "url":"http://vs-akcent.ru",
"callback":"qwerty"}
,{ "url":"http://inter-komplekt.ru",
"callback":"qwerty"}
,{ "url":"http://azbykamebeli.ru",
"callback":"qwerty"}
,{ "url":"http://komfort-kam.umi.ru",
"callback":"qwerty"}
,{ "url":"http://www.unna-office.ru",
"callback":"qwerty"}
,{ "url":"http://mebel-accent.ru",
"callback":"qwerty"}
,{ "url":"http://vasilev-v-a.tiu.ru",
"callback":"qwerty"}
,{ "url":"http://arsenalmebel.com",
"callback":"qwerty"}
,{ "url":"http://место.рф",
"callback":"qwerty"}
,{ "url":"http://www.alpha-mebel.com",
"callback":"qwerty"}
,{ "url":"http://verona-mebel.net",
"callback":"qwerty"}
,{ "url":"http://vostok-mebel.ru",
"callback":"qwerty"}
,{ "url":"http://line-p.ru",
"callback":"qwerty"}
,{ "url":"http://www.odakam.com",
"callback":"qwerty"}
,{ "url":"http://ptenec-kamchatka.ru",
"callback":"qwerty"}
,{ "url":"http://www.fm-home.ru",
"callback":"qwerty"}
,{ "url":"http://angstrem-mebel.ru",
"callback":"qwerty"}
,{ "url":"http://vpk-format.ru",
"callback":"qwerty"}
,{ "url":"http://www.fm-kids.ru",
"callback":"qwerty"}
,{ "url":"http://www.fm-kids.ru",
"callback":"qwerty"}
,{ "url":"http://www.lazurit.com",
"callback":"qwerty"}
,{ "url":"http://salon-fortuna.ru",
"callback":"qwerty"}
,{ "url":"http://papakarlo41.ru",
"callback":"qwerty"}
,{ "url":"http://design-k-studio.ru",
"callback":"qwerty"}
,{ "url":"http://www.dmi-group.ru",
"callback":"qwerty"}
,{ "url":"http://shatura.com",
"callback":"qwerty"}
,{ "url":"http://kamgabarit.ru",
"callback":"qwerty"}
,{ "url":"http://zodchie330660.ru",
"callback":"qwerty"}
,{ "url":"http://davitamebel.ru",
"callback":"qwerty"}
,{ "url":"http://www.мебельград.рф",
"callback":"qwerty"}
,{ "url":"http://www.dochkisinochki.ru",
"callback":"qwerty"}
,{ "url":"http://ogogo.ru",
"callback":"qwerty"}
,{ "url":"http://ecoprint41.ru",
"callback":"qwerty"}
,{ "url":"http://www.gammapluspk.ru",
"callback":"qwerty"}
,{ "url":"http://stuff-point.com/",
"callback":"qwerty"}
,{ "url":"http://www.kamartmuseum.ru",
"callback":"qwerty"}
,{ "url":"http://st.sergius.pravkamchatka.ru",
"callback":"qwerty"}
,{ "url":"http://pravkamchatka.ru",
"callback":"qwerty"}
,{ "url":"http://kamcnt.ru",
"callback":"qwerty"}
,{ "url":"http://kammusic.ru",
"callback":"qwerty"}
,{ "url":"http://www.kamteatr-kukol.com",
"callback":"qwerty"}
,{ "url":"http://kamteatr.com",
"callback":"qwerty"}
,{ "url":"http://pravkamchatka.ru",
"callback":"qwerty"}
,{ "url":"http://dpc.pravkamchatka.ru",
"callback":"qwerty"}
,{ "url":"http://dpc.pravkamchatka.ru/",
"callback":"qwerty"}
,{ "url":"http://музей-пке.рф",
"callback":"qwerty"}
,{ "url":"http://museum-vil.ru",
"callback":"qwerty"}
,{ "url":"http://www.tfikamchatka.ru",
"callback":"qwerty"}
,{ "url":"http://www.kamchatka-museum.ru",
"callback":"qwerty"}
,{ "url":"http://www.vulcanarium.com",
"callback":"qwerty"}
,{ "url":"http://shkola.pravelizovo.ru",
"callback":"qwerty"}
,{ "url":"http://villib.ru",
"callback":"qwerty"}
,{ "url":"http://pogranichny.wixsite.com/library4",
"callback":"qwerty"}
,{ "url":"http://lib-pk.ru",
"callback":"qwerty"}
,{ "url":"http://elizovolib.kamch.muzkult.ru | http://elizovolib.ru",
"callback":"qwerty"}
,{ "url":"http://lib-pk.ru",
"callback":"qwerty"}
,{ "url":"http://knizhkindom.com",
"callback":"qwerty"}
,{ "url":"http://www.kamlib.ru",
"callback":"qwerty"}
,{ "url":"http://www.lavka-skatertsamobranka.com",
"callback":"qwerty"}
,{ "url":"http://sulyma.ru",
"callback":"qwerty"}
,{ "url":"http://imc.pkgo.ru",
"callback":"qwerty"}
,{ "url":"http://www.novkniga.ru",
"callback":"qwerty"}
,{ "url":"http://kam-shop.ru",
"callback":"qwerty"}
,{ "url":"http://livesound.biz",
"callback":"qwerty"}
,{ "url":"http://deleon41.ru",
"callback":"qwerty"}
,{ "url":"http://winda41.ru",
"callback":"qwerty"}
,{ "url":"http://dimaestri41.ru",
"callback":"qwerty"}
,{ "url":"http://kambarshop.ru",
"callback":"qwerty"}
,{ "url":"http://www.kofeiko.ru",
"callback":"qwerty"}
,{ "url":"http://nix.ru",
"callback":"qwerty"}
,{ "url":"http://www.techno-boom.ru",
"callback":"qwerty"}
,{ "url":"http://ritm.com",
"callback":"qwerty"}
,{ "url":"http://ktl.ru",
"callback":"qwerty"}
,{ "url":"http://аймакс-сервис.рф | http://aymaks41.blizko.ru",
"callback":"qwerty"}
,{ "url":"http://kamzip.ru",
"callback":"qwerty"}
,{ "url":"http://www.dokaprint.ru",
"callback":"qwerty"}
,{ "url":"http://папирус-плюс.рф",
"callback":"qwerty"}
,{ "url":"http://картриджи41.рф",
"callback":"qwerty"}
,{ "url":"http://atribut41.ru",
"callback":"qwerty"}
,{ "url":"http://trieracentr.ru",
"callback":"qwerty"}
,{ "url":"http://anykey41.ru",
"callback":"qwerty"}
,{ "url":"http://www.kamavangard.ru",
"callback":"qwerty"}
,{ "url":"http://kam41.ru",
"callback":"qwerty"}
,{ "url":"http://allurehome-kam.ru",
"callback":"qwerty"}
,{ "url":"http://www.zepter.ru",
"callback":"qwerty"}
,{ "url":"http://техника21.рф",
"callback":"qwerty"}
,{ "url":"http://www.m.komtrade.ru",
"callback":"qwerty"}
,{ "url":"http://www.eldorado.ru",
"callback":"qwerty"}
,{ "url":"http://nt41.ru",
"callback":"qwerty"}
,{ "url":"http://marioland.ru",
"callback":"qwerty"}
,{ "url":"http://console41.ru",
"callback":"qwerty"}
,{ "url":"http://m41m.ru",
"callback":"qwerty"}
,{ "url":"http://pkgo.ru/uerio.html",
"callback":"qwerty"}
,{ "url":"http://www.333art.ru",
"callback":"qwerty"}
,{ "url":"http://photography-kopirochka70.business.site",
"callback":"qwerty"}
,{ "url":"http://fotka41.ru",
"callback":"qwerty"}
,{ "url":"http://www.shors.ru",
"callback":"qwerty"}
,{ "url":"http://oboronenergo.su",
"callback":"qwerty"}
,{ "url":"http://kamenergo.ru",
"callback":"qwerty"}
,{ "url":"http://aokes.ru",
"callback":"qwerty"}
,{ "url":"http://каммедколледж.рф",
"callback":"qwerty"}
,{ "url":"http://kpt-kamchatka.ru",
"callback":"qwerty"}
,{ "url":"http://artpk.net",
"callback":"qwerty"}
,{ "url":"http://kamchatgtu.ru",
"callback":"qwerty"}
,{ "url":"http://golden-time.ru",
"callback":"qwerty"}
,{ "url":"http://оптика-имидж.рф",
"callback":"qwerty"}
,{ "url":"http://www.rkc-pk.ru",
"callback":"qwerty"}
,{ "url":"http://kamenergo.ru",
"callback":"qwerty"}
,{ "url":"http://stepbest.wixsite.com/refreshkam",
"callback":"qwerty"}
,{ "url":"http://www.chd41.ru",
"callback":"qwerty"}
,{ "url":"http://kirby.com",
"callback":"qwerty"}
,{ "url":"http://dez-oao.ru/pu_blesk",
"callback":"qwerty"}
,{ "url":"http://kte.a5.ru",
"callback":"qwerty"}
,{ "url":"http://csm41.ru",
"callback":"qwerty"}
,{ "url":"http://expert-kamchatka.ru",
"callback":"qwerty"}
,{ "url":"http://expert-kamchatka.ru",
"callback":"qwerty"}
,{ "url":"http://kamgranit.ru",
"callback":"qwerty"}
,{ "url":"http://445501.ru",
"callback":"qwerty"}
,{ "url":"http://кам-памятники.рф",
"callback":"qwerty"}
,{ "url":"http://requiem-pk.ru",
"callback":"qwerty"}
,{ "url":"http://grave-stone41.ru",
"callback":"qwerty"}
,{ "url":"http://meddezkam.ru",
"callback":"qwerty"}
,{ "url":"http://ecohouse41.ru",
"callback":"qwerty"}
,{ "url":"http://garantdv41.ru",
"callback":"qwerty"}
,{ "url":"http://oaokes.ru",
"callback":"qwerty"}
,{ "url":"http://korenergo.ru",
"callback":"qwerty"}
,{ "url":"http://ueskam.ru",
"callback":"qwerty"}
,{ "url":"http://petropavlovsk-kamchatskiy.domofenok.ru",
"callback":"qwerty"}
,{ "url":"http://www.pickpoint.ru",
"callback":"qwerty"}
,{ "url":"http://kamrc.ru/index.php?topic=1572.0",
"callback":"qwerty"}
,{ "url":"http://www.rscc.ru",
"callback":"qwerty"}
,{ "url":"http://pokupki41.ru",
"callback":"qwerty"}
,{ "url":"http://Sp-pro100.ru",
"callback":"qwerty"}
,{ "url":"http://7sp.ru",
"callback":"qwerty"}
,{ "url":"http://100sp.ru",
"callback":"qwerty"}
,{ "url":"http://petropavlovsk-kam.kvartirka.com",
"callback":"qwerty"}
,{ "url":"http://imfast.com",
"callback":"qwerty"}
,{ "url":"http://upstudy.ru",
"callback":"qwerty"}
,{ "url":"http://am.ru",
"callback":"qwerty"}
,{ "url":"http://baza.estate",
"callback":"qwerty"}
,{ "url":"http://rubrido.ru",
"callback":"qwerty"}
,{ "url":"http://леснойресурс.рф",
"callback":"qwerty"}
,{ "url":"http://petropavlovsk-kam.dorus.ru",
"callback":"qwerty"}
,{ "url":"http://www.pk.barahla.net",
"callback":"qwerty"}
,{ "url":"http://drom.ru",
"callback":"qwerty"}
,{ "url":"http://youla.io",
"callback":"qwerty"}
,{ "url":"http://petropavlovsk-kamchatskiy.gde.ru",
"callback":"qwerty"}
,{ "url":"http://www.avito.ru",
"callback":"qwerty"}
,{ "url":"http://petropavlovsk-kamchatskiy.1001kvartira.ru",
"callback":"qwerty"}
,{ "url":"http://yourenta.ru/c-petropavlovsk",
"callback":"qwerty"}
,{ "url":"http://fenixteh.ru",
"callback":"qwerty"}
,{ "url":"http://kamservice.ru",
"callback":"qwerty"}
,{ "url":"http://www.dns-shop.ru",
"callback":"qwerty"}
,{ "url":"http://qeiron.ru",
"callback":"qwerty"}
,{ "url":"http://sites41.refakt.ru | http://kontekst41.refakt.ru",
"callback":"qwerty"}
,{ "url":"http://rosintersite.ru",
"callback":"qwerty"}
,{ "url":"http://molchstudio.ru",
"callback":"qwerty"}
,{ "url":"http://fotkam41.com",
"callback":"qwerty"}
,{ "url":"http://gepart-city.ru",
"callback":"qwerty"}
,{ "url":"http://ibgkam.ru",
"callback":"qwerty"}
,{ "url":"http://levinst.ru",
"callback":"qwerty"}
,{ "url":"http://pk.pechati5.ru",
"callback":"qwerty"}
,{ "url":"http://камюрист.рф",
"callback":"qwerty"}
,{ "url":"http://itc.kamgov.ru | http://ca.kamgov.ru",
"callback":"qwerty"}
,{ "url":"http://distsoft.ru",
"callback":"qwerty"}
,{ "url":"http://www.inkkam.ru",
"callback":"qwerty"}
,{ "url":"http://www.kitc.ru",
"callback":"qwerty"}
,{ "url":"http://terabyte-t.ru",
"callback":"qwerty"}
,{ "url":"http://www.kompas41.ru | http://eshop.kompas41.ru",
"callback":"qwerty"}
,{ "url":"http://inko.ru",
"callback":"qwerty"}
,{ "url":"http://pochta.ru",
"callback":"qwerty"}
,{ "url":"http://www.pochta.ru",
"callback":"qwerty"}
,{ "url":"http://pochta.ru",
"callback":"qwerty"}
,{ "url":"http://pochta.ru",
"callback":"qwerty"}
,{ "url":"http://pochta.ru",
"callback":"qwerty"}
,{ "url":"http://pochta.ru",
"callback":"qwerty"}
,{ "url":"http://pochta.ru",
"callback":"qwerty"}
,{ "url":"http://pochta.ru",
"callback":"qwerty"}
,{ "url":"http://pochta.ru",
"callback":"qwerty"}
,{ "url":"http://pochta.ru",
"callback":"qwerty"}
,{ "url":"http://pochta.ru",
"callback":"qwerty"}
,{ "url":"http://pochta.ru",
"callback":"qwerty"}
,{ "url":"http://pochta.ru",
"callback":"qwerty"}
,{ "url":"http://pochta.ru",
"callback":"qwerty"}
,{ "url":"http://www.pochta.ru",
"callback":"qwerty"}
,{ "url":"http://www.pochta.ru",
"callback":"qwerty"}
,{ "url":"http://pochta.ru",
"callback":"qwerty"}
,{ "url":"http://pochta.ru",
"callback":"qwerty"}
,{ "url":"http://pochta.ru",
"callback":"qwerty"}
,{ "url":"http://pochta.ru",
"callback":"qwerty"}
,{ "url":"http://pochta.ru",
"callback":"qwerty"}
,{ "url":"http://pochta.ru",
"callback":"qwerty"}
,{ "url":"http://pochta.ru",
"callback":"qwerty"}
,{ "url":"http://pochta.ru",
"callback":"qwerty"}
,{ "url":"http://pochta.ru",
"callback":"qwerty"}
,{ "url":"http://pochta.ru",
"callback":"qwerty"}
,{ "url":"http://pochta.ru",
"callback":"qwerty"}
,{ "url":"http://pochta.ru",
"callback":"qwerty"}
,{ "url":"http://www.rambler.ru",
"callback":"qwerty"}
,{ "url":"http://vp.ru",
"callback":"qwerty"}
,{ "url":"http://yota.ru",
"callback":"qwerty"}
,{ "url":"http://www.spektr.ipkam.ru",
"callback":"qwerty"}
,{ "url":"http://kvartal-center.ru",
"callback":"qwerty"}
,{ "url":"http://comp41.ru",
"callback":"qwerty"}
,{ "url":"http://sat.ds41.ru",
"callback":"qwerty"}
,{ "url":"http://ctcom.systems",
"callback":"qwerty"}
,{ "url":"http://tarifkam.ru",
"callback":"qwerty"}
,{ "url":"http://www.firma88.ru",
"callback":"qwerty"}
,{ "url":"http://www.beeline.ru",
"callback":"qwerty"}
,{ "url":"http://petropalovsk-kamchatskij.domotekhnika.ru",
"callback":"qwerty"}
,{ "url":"http://www.frau-technica.ru",
"callback":"qwerty"}
,{ "url":"http://www.kamsputnik.ru",
"callback":"qwerty"}
,{ "url":"http://shop.tele2.ru",
"callback":"qwerty"}
,{ "url":"http://uznay-prezidenta.ru",
"callback":"qwerty"}
,{ "url":"http://kompaskreditov.ru",
"callback":"qwerty"}
,{ "url":"http://baza.estate",
"callback":"qwerty"}
,{ "url":"http://bank-advisor.ru",
"callback":"qwerty"}
,{ "url":"http://zakupki.kamgov.ru",
"callback":"qwerty"}
,{ "url":"http://kam-edu.ru",
"callback":"qwerty"}
,{ "url":"http://visitkamchatka.ru",
"callback":"qwerty"}
,{ "url":"http://opkam.ru",
"callback":"qwerty"}
,{ "url":"http://kamgov.ru",
"callback":"qwerty"}
,{ "url":"http://profi.ru",
"callback":"qwerty"}
,{ "url":"http://www.svadba41.ru",
"callback":"qwerty"}
,{ "url":"http://kris41.ru",
"callback":"qwerty"}
,{ "url":"http://edu.pkgo.ru",
"callback":"qwerty"}
,{ "url":"http://www.pkportal.ru",
"callback":"qwerty"}
,{ "url":"http://stroika.ru",
"callback":"qwerty"}
,{ "url":"http://www.kamchatsky-krai.ru",
"callback":"qwerty"}
,{ "url":"http://baza41.ru",
"callback":"qwerty"}
,{ "url":"http://portal-uspeha.ru",
"callback":"qwerty"}
,{ "url":"http://kamchatka_krai.izbirkom.ru",
"callback":"qwerty"}
,{ "url":"http://www.poluostrov-kamchatka.ru",
"callback":"qwerty"}
,{ "url":"http://vestipk.ru",
"callback":"qwerty"}
,{ "url":"http://ipoteka.domclick.ru/?utm_campaign=ipoteka_frk_mar_apr_2018_videobranding&utm_source=2gis&utm_medium=cpm&prod=4&.ru&dclid=CL_y_M_kkdoCFVdNGAodc",
"callback":"qwerty"}
,{ "url":"http://www.kam24.ru",
"callback":"qwerty"}
,{ "url":"http://www.city-pages.info | http://kupon.city-pages.info",
"callback":"qwerty"}
,{ "url":"http://bitkam.ru",
"callback":"qwerty"}
,{ "url":"http://300205.ru",
"callback":"qwerty"}
,{ "url":"http://www.kamtv.ru",
"callback":"qwerty"}
,{ "url":"http://elizovotv.ru",
"callback":"qwerty"}
,{ "url":"http://kamchatka.megafon.ru",
"callback":"qwerty"}
,{ "url":"http://edu.ru",
"callback":"qwerty"}
,{ "url":"http://pravo.gov.ru",
"callback":"qwerty"}
,{ "url":"http://spas-extreme.ru",
"callback":"qwerty"}
,{ "url":"http://aiss.gov.ru",
"callback":"qwerty"}
,{ "url":"http://back2russia.ru",
"callback":"qwerty"}
,{ "url":"http://www.kremlin.ru",
"callback":"qwerty"}
,{ "url":"http://www.government.ru",
"callback":"qwerty"}
,{ "url":"http://www.112info.ru",
"callback":"qwerty"}
,{ "url":"http://gia.edu.ru",
"callback":"qwerty"}
,{ "url":"http://investkamchatka.ru",
"callback":"qwerty"}
,{ "url":"http://prava41.ru",
"callback":"qwerty"}
,{ "url":"http://bus.gov.ru",
"callback":"qwerty"}
,{ "url":"http://premier.gov.ru",
"callback":"qwerty"}
,{ "url":"http://www.uznai-prezidenta.ru",
"callback":"qwerty"}
,{ "url":"http://ksp41.ru",
"callback":"qwerty"}
,{ "url":"http://www.gosuslugi.ru | http://gosuslugi41.ru",
"callback":"qwerty"}
,{ "url":"http://profit-kam.ru",
"callback":"qwerty"}
,{ "url":"http://yulax.ru",
"callback":"qwerty"}
,{ "url":"http://ooo-dominion.ru",
"callback":"qwerty"}
,{ "url":"http://www.bsystem41.ru",
"callback":"qwerty"}
,{ "url":"http://bga-service.com",
"callback":"qwerty"}
,{ "url":"http://bit-serv.ru",
"callback":"qwerty"}
,{ "url":"http://www.kambuh.ru",
"callback":"qwerty"}
,{ "url":"http://winda41.ru",
"callback":"qwerty"}
,{ "url":"http://vesninsoft.ru",
"callback":"qwerty"}
,{ "url":"http://shop.amn-computers.ru",
"callback":"qwerty"}
,{ "url":"http://www.pultovik41.ru",
"callback":"qwerty"}
,{ "url":"http://tarifkam.ru",
"callback":"qwerty"}
,{ "url":"http://allomart.ru",
"callback":"qwerty"}
,{ "url":"http://svyaznoy.ru",
"callback":"qwerty"}
,{ "url":"http://euroset.ru",
"callback":"qwerty"}
,{ "url":"http://kamchatka.megafon.ru",
"callback":"qwerty"}
,{ "url":"http://fullservice41.ru",
"callback":"qwerty"}
,{ "url":"http://mobilspeed.ru",
"callback":"qwerty"}
,{ "url":"http://www.itkam41.ru",
"callback":"qwerty"}
,{ "url":"http://www.ishop-retail.com",
"callback":"qwerty"}
,{ "url":"http://shop.huawei.ru/?utm_source=2gis&utm_medium=cpm_card_bd&utm_term=&utm_content=&utm_campaign=2018Q2_2Gis_Huawei",
"callback":"qwerty"}
,{ "url":"http://kamkass.ru",
"callback":"qwerty"}
,{ "url":"http://kontur-vil.ru",
"callback":"qwerty"}
,{ "url":"http://torgovayatehnika.ru",
"callback":"qwerty"}
,{ "url":"http://rmk.plus",
"callback":"qwerty"}
,{ "url":"http://rmk.plus",
"callback":"qwerty"}
,{ "url":"http://kamchatkairo.ru",
"callback":"qwerty"}
,{ "url":"http://kamtechno.ru",
"callback":"qwerty"}
,{ "url":"http://itfriendz.ru",
"callback":"qwerty"}
,{ "url":"http://cto41.ru",
"callback":"qwerty"}
,{ "url":"http://softdigi.ru | http://softdigi.com",
"callback":"qwerty"}
,{ "url":"http://www.program1ct.ru",
"callback":"qwerty"}
,{ "url":"http://spacecrabs.ru",
"callback":"qwerty"}
,{ "url":"http://www.kamca.ru",
"callback":"qwerty"}
,{ "url":"http://tensor.ru | http://sbis.ru",
"callback":"qwerty"}
,{ "url":"http://bazaronline.com",
"callback":"qwerty"}
,{ "url":"http://www.veska.ru",
"callback":"qwerty"}
,{ "url":"http://rt.ru/light_plus?utm_source=2gis&utm_medium=cpc&utm_campaign=link_petropavlovskkamchatskiy",
"callback":"qwerty"}
,{ "url":"http://hotlead.io",
"callback":"qwerty"}
,{ "url":"http://enter-pk.ru",
"callback":"qwerty"}
,{ "url":"http://www.iks.ru",
"callback":"qwerty"}
,{ "url":"http://www.rt.ru/b2b?utm_source=2gis&utm_medium=referal&utm_campaign=b2b_kartochka-kontakti_dlv_Petropavlovsk",
"callback":"qwerty"}
,{ "url":"http://www.yaslinskiygroup.ru",
"callback":"qwerty"}
,{ "url":"http://www.kuoza.ru",
"callback":"qwerty"}
,{ "url":"http://www.iraphoto.wix.com/foto",
"callback":"qwerty"}
,{ "url":"http://www.cerber.group",
"callback":"qwerty"}
,{ "url":"http://restudio.pro",
"callback":"qwerty"}
,{ "url":"http://perspektiva41.ru",
"callback":"qwerty"}
,{ "url":"http://weddingkam.ru",
"callback":"qwerty"}
,{ "url":"http://41svadba.ru | http://41свадьба.рф",
"callback":"qwerty"}
,{ "url":"http://roll-express.com",
"callback":"qwerty"}
,{ "url":"http://club-strike.ru",
"callback":"qwerty"}
,{ "url":"http://straykbol.com",
"callback":"qwerty"}
,{ "url":"http://paintball-kamchatka.ru",
"callback":"qwerty"}
,{ "url":"http://rollrockhall.ru/%D1%80%D0%BE%D0%BB%D0%BB%D0%B5%D1%80%D0%B4%D1%80%D0%BE%D0%BC/",
"callback":"qwerty"}
,{ "url":"http://www.petropavlovsk-hotel.ru",
"callback":"qwerty"}
,{ "url":"http://petrovskii-p-k.ru",
"callback":"qwerty"}
,{ "url":"http://sanmarino.nethouse.ru",
"callback":"qwerty"}
,{ "url":"http://stoloto.ru/",
"callback":"qwerty"}
,{ "url":"http://kamchatkatravers.ru | http://kamchatka-fishing.ru",
"callback":"qwerty"}
,{ "url":"http://orlan-kamchatka.ru",
"callback":"qwerty"}
,{ "url":"http://redrivers.ru",
"callback":"qwerty"}
,{ "url":"http://kamchatkatrip.com",
"callback":"qwerty"}
,{ "url":"http://concertpk.ru",
"callback":"qwerty"}
,{ "url":"http://firekamchatka.ru",
"callback":"qwerty"}
,{ "url":"http://rozovyi-ezh41.ru",
"callback":"qwerty"}
,{ "url":"http://petipa.ru",
"callback":"qwerty"}
,{ "url":"http://www.laserkam.ru",
"callback":"qwerty"}
,{ "url":"http://kaminfotour.ru",
"callback":"qwerty"}
,{ "url":"http://www.kletka.club",
"callback":"qwerty"}
,{ "url":"http://escplan.ru",
"callback":"qwerty"}
,{ "url":"http://norakrolika.ru",
"callback":"qwerty"}
,{ "url":"http://www.kamchatka.nik-show.ru",
"callback":"qwerty"}
,{ "url":"http://kamcnt.ru",
"callback":"qwerty"}
,{ "url":"http://kamcnt.ru",
"callback":"qwerty"}
,{ "url":"http://www.agrotek.ru",
"callback":"qwerty"}
,{ "url":"http://piramida-pk.ru",
"callback":"qwerty"}
,{ "url":"http://www.kamkino.ru",
"callback":"qwerty"}
,{ "url":"http://kamprime.ru",
"callback":"qwerty"}
,{ "url":"http://www.pr-prosto.ru",
"callback":"qwerty"}
,{ "url":"http://coffee-like.com",
"callback":"qwerty"}
,{ "url":"http://cinnabonrussia.com",
"callback":"qwerty"}
,{ "url":"http://pit-pit.ru",
"callback":"qwerty"}
,{ "url":"http://cucarachacam.ru",
"callback":"qwerty"}
,{ "url":"http://www.hesburger.ru",
"callback":"qwerty"}
,{ "url":"http://friendsburger.ru",
"callback":"qwerty"}
,{ "url":"http://marmaris-u.ru",
"callback":"qwerty"}
,{ "url":"http://cafehoma.ru",
"callback":"qwerty"}
,{ "url":"http://www.cafe.kvartal-center.ru",
"callback":"qwerty"}
,{ "url":"http://www.kamramen.ru",
"callback":"qwerty"}
,{ "url":"http://art.cafe.globus",
"callback":"qwerty"}
,{ "url":"http://www.geyser-hotel.ru",
"callback":"qwerty"}
,{ "url":"http://cafe-bulvar.com",
"callback":"qwerty"}
,{ "url":"http://www.idelveis.com",
"callback":"qwerty"}
,{ "url":"http://www.avachahotel.ru",
"callback":"qwerty"}
,{ "url":"http://zooparkpk.ru",
"callback":"qwerty"}
,{ "url":"http://www.pirog41.biz",
"callback":"qwerty"}
,{ "url":"http://440022.ru",
"callback":"qwerty"}
,{ "url":"http://www.483000.ru",
"callback":"qwerty"}
,{ "url":"http://rollrockhall.ru",
"callback":"qwerty"}
,{ "url":"http://kamchatka-sushi.ru",
"callback":"qwerty"}
,{ "url":"http://sheffroll.ru",
"callback":"qwerty"}
,{ "url":"http://222505.рф",
"callback":"qwerty"}
,{ "url":"http://bulvar-express.com",
"callback":"qwerty"}
,{ "url":"http://roll-express.com",
"callback":"qwerty"}
,{ "url":"http://murakami-san.ru",
"callback":"qwerty"}
,{ "url":"http://ситипицца41.рф",
"callback":"qwerty"}
,{ "url":"http://sdk-talant.ru",
"callback":"qwerty"}
,{ "url":"http://dk-ritm.ru",
"callback":"qwerty"}
,{ "url":"http://sdk-talant.ru",
"callback":"qwerty"}
,{ "url":"http://sdk-koryaki.kamch.muzkult.ru",
"callback":"qwerty"}
,{ "url":"http://galaxydk.ru/kontakty/",
"callback":"qwerty"}
,{ "url":"http://ckdviluchinsk.ru",
"callback":"qwerty"}
,{ "url":"http://камрдк.рф",
"callback":"qwerty"}
,{ "url":"http://dk-yunost.kamch.muzkult.ru",
"callback":"qwerty"}
,{ "url":"http://просоль.рф",
"callback":"qwerty"}
,{ "url":"http://kamratibor.ru",
"callback":"qwerty"}
,{ "url":"http://www.станцияют.рф",
"callback":"qwerty"}
,{ "url":"http://roza41.ru",
"callback":"qwerty"}
,{ "url":"http://kamgift.kamch.muzkult.ru",
"callback":"qwerty"}
,{ "url":"http://puzzlemuzzle.ru",
"callback":"qwerty"}
,{ "url":"http://kamdut.ru",
"callback":"qwerty"}
,{ "url":"http://krctc.edu.ru",
"callback":"qwerty"}
,{ "url":"http://цдод-луч.рф",
"callback":"qwerty"}
,{ "url":"http://kamchatka.startjunior.ru",
"callback":"qwerty"}
,{ "url":"http://yunost-pk.ru",
"callback":"qwerty"}
,{ "url":"http://cvrpk.ucoz.org",
"callback":"qwerty"}
,{ "url":"http://kamddt.ru",
"callback":"qwerty"}
,{ "url":"http://www.rassvetykamchatki.ru | http://рассветы-камчатки.рф",
"callback":"qwerty"}
,{ "url":"http://seroglazka-ckd.ru",
"callback":"qwerty"}
,{ "url":"http://www.sivuchclub.ru",
"callback":"qwerty"}
,{ "url":"http://www.diving-kam.ru",
"callback":"qwerty"}
,{ "url":"http://orca-diving.ru",
"callback":"qwerty"}
,{ "url":"http://www.baltbet.ru",
"callback":"qwerty"}
,{ "url":"http://pivnovbeer.ru",
"callback":"qwerty"}
,{ "url":"http://arthotel-kamchatka.ru",
"callback":"qwerty"}
,{ "url":"http://uyutkam.ru",
"callback":"qwerty"}
,{ "url":"http://harats.ru",
"callback":"qwerty"}
,{ "url":"http://butcherkamchatka.ru",
"callback":"qwerty"}
,{ "url":"http://ст-замок.рф",
"callback":"qwerty"}
,{ "url":"http://zolotoy-yakor.ru",
"callback":"qwerty"}
,{ "url":"http://ekoprodukt41.com",
"callback":"qwerty"}
,{ "url":"http://xamam11.ru",
"callback":"qwerty"}
,{ "url":"http://allaboutkamchatka.ru/gostevoj-dom",
"callback":"qwerty"}
,{ "url":"http://kamreshouse.ru",
"callback":"qwerty"}
,{ "url":"http://proffi41.com",
"callback":"qwerty"}
,{ "url":"http://belkamtour.ru",
"callback":"qwerty"}
,{ "url":"http://baza-lotos-kamchatka.ru",
"callback":"qwerty"}
,{ "url":"http://www.kamvillage.com",
"callback":"qwerty"}
,{ "url":"http://flystudio41.ru",
"callback":"qwerty"}
,{ "url":"http://r41.fss.ru",
"callback":"qwerty"}
,{ "url":"http://kamtfoms.ru",
"callback":"qwerty"}
,{ "url":"http://rosreestr.ru",
"callback":"qwerty"}
,{ "url":"http://to41.minjust.ru",
"callback":"qwerty"}
,{ "url":"http://rai.kamchatka.ru",
"callback":"qwerty"}
,{ "url":"http://kamstat.gks.ru",
"callback":"qwerty"}
,{ "url":"http://rai.kamchatka.ru",
"callback":"qwerty"}
,{ "url":"http://amurbvu.ru",
"callback":"qwerty"}
,{ "url":"http://kspemr.ru",
"callback":"qwerty"}
,{ "url":"http://kamgov.ru/appr",
"callback":"qwerty"}
,{ "url":"http://dvgosmornadzor.ru",
"callback":"qwerty"}
,{ "url":"http://www.tfikamchatka.ru",
"callback":"qwerty"}
,{ "url":"http://41.rkn.gov.ru",
"callback":"qwerty"}
,{ "url":"http://www.ugadn27.tu.rostransnadzor.ru",
"callback":"qwerty"}
,{ "url":"http://свту.рф",
"callback":"qwerty"}
,{ "url":"http://www.kamchatka.mid.ru",
"callback":"qwerty"}
,{ "url":"http://свту.рф",
"callback":"qwerty"}
,{ "url":"http://tu41.rosim.ru",
"callback":"qwerty"}
,{ "url":"http://сврв.рф",
"callback":"qwerty"}
,{ "url":"http://kamchatka.fas.gov.ru",
"callback":"qwerty"}
,{ "url":"http://41.fsin.su",
"callback":"qwerty"}
,{ "url":"http://ufps.kamchatka.ru",
"callback":"qwerty"}
,{ "url":"http://kadastr.ru",
"callback":"qwerty"}
,{ "url":"http://41.rospotrebnadzor.ru",
"callback":"qwerty"}
,{ "url":"http://www.nalog.ru",
"callback":"qwerty"}
,{ "url":"http://kamchatka.roskazna.ru",
"callback":"qwerty"}
,{ "url":"http://41.мвд.рф",
"callback":"qwerty"}
,{ "url":"http://dvtu.customs.ru",
"callback":"qwerty"}
,{ "url":"http://11.kmch.msudrf.ru",
"callback":"qwerty"}
,{ "url":"http://4.kmch.msudrf.ru",
"callback":"qwerty"}
,{ "url":"http://13.kmch.msudrf.ru",
"callback":"qwerty"}
,{ "url":"http://7.kmch.msudrf.ru",
"callback":"qwerty"}
,{ "url":"http://10.kmch.msudrf.ru",
"callback":"qwerty"}
,{ "url":"http://9.kmch.msudrf.ru",
"callback":"qwerty"}
,{ "url":"http://14.kmch.msudrf.ru",
"callback":"qwerty"}
,{ "url":"http://5.kmch.msudrf.ru",
"callback":"qwerty"}
,{ "url":"http://6.kmch.msudrf.ru",
"callback":"qwerty"}
,{ "url":"http://2.kmch.msudrf.ru",
"callback":"qwerty"}
,{ "url":"http://12.kmch.msudrf.ru",
"callback":"qwerty"}
,{ "url":"http://20.kmch.msudrf.ru",
"callback":"qwerty"}
,{ "url":"http://16.kmch.msudrf.ru",
"callback":"qwerty"}
,{ "url":"http://22.kmch.msudrf.ru",
"callback":"qwerty"}
,{ "url":"http://1.kmch.msudrf.ru",
"callback":"qwerty"}
,{ "url":"http://21.kmch.msudrf.ru",
"callback":"qwerty"}
,{ "url":"http://3.kmch.msudrf.ru",
"callback":"qwerty"}
,{ "url":"http://24.kmch.msudrf.ru",
"callback":"qwerty"}
,{ "url":"http://17.kmch.msudrf.ru",
"callback":"qwerty"}
,{ "url":"http://23.kmch.msudrf.ru",
"callback":"qwerty"}
,{ "url":"http://15.kmch.msudrf.ru",
"callback":"qwerty"}
,{ "url":"http://oblsud.kam.sudrf.ru",
"callback":"qwerty"}
,{ "url":"http://kam.vkks.ru",
"callback":"qwerty"}
,{ "url":"http://25.kmch.msudrf.ru",
"callback":"qwerty"}
,{ "url":"http://viluchinsky.kam.sudrf.ru",
"callback":"qwerty"}
,{ "url":"http://19.kmch.msudrf.ru",
"callback":"qwerty"}
,{ "url":"http://elizovsky.kam.sudrf.ru",
"callback":"qwerty"}
,{ "url":"http://www.kamchatka.arbitr.ru",
"callback":"qwerty"}
,{ "url":"http://p-kamchatsky.kam.sudrf.ru",
"callback":"qwerty"}
,{ "url":"http://8.kmch.msudrf.ru",
"callback":"qwerty"}
,{ "url":"http://kcs41.ru | http://kamexpert.ru",
"callback":"qwerty"}
,{ "url":"http://kamsoccentr.ru",
"callback":"qwerty"}
,{ "url":"http://ktson.ru",
"callback":"qwerty"}
,{ "url":"http://pkgo.ru/uerio.html",
"callback":"qwerty"}
,{ "url":"http://kamlib.ru",
"callback":"qwerty"}
,{ "url":"http://social-center.ru",
"callback":"qwerty"}
,{ "url":"http://kcsonpkgo.ru",
"callback":"qwerty"}
,{ "url":"http://r41.fssprus.ru | http://fssprus.ru/iss/ip",
"callback":"qwerty"}
,{ "url":"http://fssprus.ru/iss/ip | http://fssprus.ru",
"callback":"qwerty"}
,{ "url":"http://r41.fssprus.ru",
"callback":"qwerty"}
,{ "url":"http://www.rabota.kamchatka.ru",
"callback":"qwerty"}
,{ "url":"http://agzanyat.kamgov.ru",
"callback":"qwerty"}
,{ "url":"http://kamchatka.sledcom.ru",
"callback":"qwerty"}
,{ "url":"http://41.sledcom.ru",
"callback":"qwerty"}
,{ "url":"http://kamchatka.sledcom.ru",
"callback":"qwerty"}
,{ "url":"http://kamchatka.sledcom.ru",
"callback":"qwerty"}
,{ "url":"http://kamprok.ru",
"callback":"qwerty"}
,{ "url":"http://ombudsmanbiz.ru/kamchatskij-kraj | http://www.prava41.ru/upolnomochenniy-po-zaschite-prav-predprinimateley/",
"callback":"qwerty"}
,{ "url":"http://prava41.ru",
"callback":"qwerty"}
,{ "url":"http://prava41.ru",
"callback":"qwerty"}
,{ "url":"http://prava41.ru",
"callback":"qwerty"}
,{ "url":"http://prava41.ru",
"callback":"qwerty"}
,{ "url":"http://admelizovo.ru",
"callback":"qwerty"}
,{ "url":"http://vkalashnikov.com",
"callback":"qwerty"}
,{ "url":"http://dumaemr.ru",
"callback":"qwerty"}
,{ "url":"http://duma.pkgo.ru",
"callback":"qwerty"}
,{ "url":"http://www.kamgov.ru/minselhoz",
"callback":"qwerty"}
,{ "url":"http://www.kamgov.ru/secretariat",
"callback":"qwerty"}
,{ "url":"http://www.kamgov.ru/control",
"callback":"qwerty"}
,{ "url":"http://www.kamgov.ru/uprdela",
"callback":"qwerty"}
,{ "url":"http://www.kamgov.ru/minecon",
"callback":"qwerty"}
,{ "url":"http://www.kamgov.ru/press",
"callback":"qwerty"}
,{ "url":"http://www.kamgov.ru/buh",
"callback":"qwerty"}
,{ "url":"http://www.kamgov.ru",
"callback":"qwerty"}
,{ "url":"http://www.kamgov.ru/minzkh",
"callback":"qwerty"}
,{ "url":"http://www.kamgov.ru/kadry",
"callback":"qwerty"}
,{ "url":"http://www.kamgov.ru/pravo",
"callback":"qwerty"}
,{ "url":"http://dfo.gov.ru",
"callback":"qwerty"}
,{ "url":"http://www.kamgov.ru/agpublic",
"callback":"qwerty"}
,{ "url":"http://www.kamgov.ru/minsp",
"callback":"qwerty"}
,{ "url":"http://www.kamgov.ru/agais | http://agais.kamgov.ru",
"callback":"qwerty"}
,{ "url":"http://www.kamgov.ru/apparat",
"callback":"qwerty"}
,{ "url":"http://kamgov.ru",
"callback":"qwerty"}
,{ "url":"http://www.kamgov.ru/minfin",
"callback":"qwerty"}
,{ "url":"http://www.kamgov.ru/minter",
"callback":"qwerty"}
,{ "url":"http://www.kamgov.ru/minstroy",
"callback":"qwerty"}
,{ "url":"http://kamchatka.gov.ru | http://visitkamchatka.ru",
"callback":"qwerty"}
,{ "url":"http://kamchatka.gov.ru",
"callback":"qwerty"}
,{ "url":"http://www.kamgov.ru/mingosim",
"callback":"qwerty"}
,{ "url":"http://www.kamgov.ru/agmirsud",
"callback":"qwerty"}
,{ "url":"http://www.kamgov.ru/minprir",
"callback":"qwerty"}
,{ "url":"http://www.kamgov.ru/mintrans",
"callback":"qwerty"}
,{ "url":"http://www.kamgov.ru/minsport",
"callback":"qwerty"}
,{ "url":"http://kamgov.ru/index.php?cont=oiv_din&menu=4&menu2=0&id=172",
"callback":"qwerty"}
,{ "url":"http://www.kamgov.ru/mintrud",
"callback":"qwerty"}
,{ "url":"http://www.kamgov.ru/minobraz",
"callback":"qwerty"}
,{ "url":"http://www.rosminzdrav.ru | http://www.kamgov.ru/minzdrav",
"callback":"qwerty"}
,{ "url":"http://www.kamchatka.gov.ru",
"callback":"qwerty"}
,{ "url":"http://kprf-kamchatka.ru",
"callback":"qwerty"}
,{ "url":"http://ldpr.ru | http://kamchatka.ldpr.ru",
"callback":"qwerty"}
,{ "url":"http://kamchatka.er.ru",
"callback":"qwerty"}
,{ "url":"http://www.pfrf.ru",
"callback":"qwerty"}
,{ "url":"http://www.pfrf.ru",
"callback":"qwerty"}
,{ "url":"http://www.pfrf.ru",
"callback":"qwerty"}
,{ "url":"http://www.pfrf.ru",
"callback":"qwerty"}
,{ "url":"http://kamchatka.gov.ru",
"callback":"qwerty"}
,{ "url":"http://дфоут.мвд.рф",
"callback":"qwerty"}
,{ "url":"http://41.мвд.рф",
"callback":"qwerty"}
,{ "url":"http://41.мвд.рф",
"callback":"qwerty"}
,{ "url":"http://dalnedra.ru",
"callback":"qwerty"}
,{ "url":"http://kmtu-vt.ru",
"callback":"qwerty"}
,{ "url":"http://41reg.roszdravnadzor.ru",
"callback":"qwerty"}
,{ "url":"http://kamgov.ru",
"callback":"qwerty"}
,{ "url":"http://dvost.gosnadzor.ru",
"callback":"qwerty"}
,{ "url":"http://www.kamgov.ru",
"callback":"qwerty"}
,{ "url":"http://www.komandorsky.ru",
"callback":"qwerty"}
,{ "url":"http://www.wildkamchatka.ru",
"callback":"qwerty"}
,{ "url":"http://clati-dv.ru",
"callback":"qwerty"}
,{ "url":"http://www.wwf.ru",
"callback":"qwerty"}
,{ "url":"http://www.kamgov.ru/agles/subordinate-entity/structure?id=481",
"callback":"qwerty"}
,{ "url":"http://www.vulcanikamchatki.ru",
"callback":"qwerty"}
,{ "url":"http://www.kronoki.ru",
"callback":"qwerty"}
,{ "url":"http://kamchatka.gov.ru",
"callback":"qwerty"}
,{ "url":"http://www.platon.ru",
"callback":"qwerty"}
,{ "url":"http://41.mvd.ru",
"callback":"qwerty"}
,{ "url":"http://41.мвд.рф",
"callback":"qwerty"}
,{ "url":"http://41.мвд.рф",
"callback":"qwerty"}
,{ "url":"http://41.мвд.рф",
"callback":"qwerty"}
,{ "url":"http://41.мвд.рф",
"callback":"qwerty"}
,{ "url":"http://41.мвд.рф",
"callback":"qwerty"}
,{ "url":"http://gkhkontrol.ru",
"callback":"qwerty"}
,{ "url":"http://ruy.ru",
"callback":"qwerty"}
,{ "url":"http://bbratstvo41.ru",
"callback":"qwerty"}
,{ "url":"http://deloros-kam.ru",
"callback":"qwerty"}
,{ "url":"http://www.oroomik.ru",
"callback":"qwerty"}
,{ "url":"http://kamko-vep.ru",
"callback":"qwerty"}
,{ "url":"http://www.sportunros41.ru",
"callback":"qwerty"}
,{ "url":"http://www.kamchatkaloppet.ru",
"callback":"qwerty"}
,{ "url":"http://mger2020.ru",
"callback":"qwerty"}
,{ "url":"http://spravedlivo.center",
"callback":"qwerty"}
,{ "url":"http://www.пргу-камчатка.рф",
"callback":"qwerty"}
,{ "url":"http://profkam.ru",
"callback":"qwerty"}
,{ "url":"http://asi.ru",
"callback":"qwerty"}
,{ "url":"http://www.fbuz41.ru",
"callback":"qwerty"}
,{ "url":"http://www.vdpokam.ru",
"callback":"qwerty"}
,{ "url":"http://notarykamchatka.ru",
"callback":"qwerty"}
,{ "url":"http://www.nalog.ru/rn41/ifns/imns41_02",
"callback":"qwerty"}
,{ "url":"http://nalog.ru",
"callback":"qwerty"}
,{ "url":"http://www.41.fsin.su",
"callback":"qwerty"}
,{ "url":"http://kamgov.ru",
"callback":"qwerty"}
,{ "url":"http://kamgov.ru",
"callback":"qwerty"}
,{ "url":"http://www.ksp-kam.ru",
"callback":"qwerty"}
,{ "url":"http://kamgov.ru",
"callback":"qwerty"}
,{ "url":"http://www.kamgov.ru",
"callback":"qwerty"}
,{ "url":"http://41.mchs.gov.ru/folder/517564",
"callback":"qwerty"}
,{ "url":"http://41.fsin.su",
"callback":"qwerty"}
,{ "url":"http://git41.rostrud.ru",
"callback":"qwerty"}
,{ "url":"http://kamchatka-krai.izbirkom.ru",
"callback":"qwerty"}
,{ "url":"http://pkgo.ru",
"callback":"qwerty"}
,{ "url":"http://zaksobr.kamchatka.ru",
"callback":"qwerty"}
,{ "url":"http://www.kamgov.ru/agzags/informacia-o-prieme-grazdan-agentstvo-zapisi-aktov-grazdanskogo-sostoania-kamcatskogo-kraa | http://agzags.kamgov.ru",
"callback":"qwerty"}
,{ "url":"http://www.pdipi.ru",
"callback":"qwerty"}
,{ "url":"http://приютдлядетей.рф",
"callback":"qwerty"}
,{ "url":"http://едди.рф",
"callback":"qwerty"}
,{ "url":"http://kamchatka.gov.ru/index.php?cont=oiv_din&menu=4&menu2=0&id=185",
"callback":"qwerty"}
,{ "url":"http://41.мвд.рф",
"callback":"qwerty"}
,{ "url":"http://kammeteo.ru",
"callback":"qwerty"}
,{ "url":"http://гибдд.xn--p1ai/r/41/",
"callback":"qwerty"}
,{ "url":"http://гибдд.xn--p1ai/r/41/",
"callback":"qwerty"}
,{ "url":"http://www.fond-rodnik.ru",
"callback":"qwerty"}
,{ "url":"http://savethelife.ru",
"callback":"qwerty"}
,{ "url":"http://pkgo.ru | http://vmeste.pkgo.ru",
"callback":"qwerty"}
,{ "url":"http://pkgo.ru",
"callback":"qwerty"}
,{ "url":"http://www.viluchinsk-city.ru",
"callback":"qwerty"}
,{ "url":"http://pkgo.ru",
"callback":"qwerty"}
,{ "url":"http://pkgo.ru",
"callback":"qwerty"}
,{ "url":"http://pkgo.ru",
"callback":"qwerty"}
,{ "url":"http://elizovomr.ru",
"callback":"qwerty"}
,{ "url":"http://elizovomr.ru",
"callback":"qwerty"}
,{ "url":"http://elizovomr.ru",
"callback":"qwerty"}
,{ "url":"http://elizovomr.ru",
"callback":"qwerty"}
,{ "url":"http://admelizovo.ru",
"callback":"qwerty"}
,{ "url":"http://41.mchs.gov.ru",
"callback":"qwerty"}
,{ "url":"http://yadoveray.ru",
"callback":"qwerty"}
,{ "url":"http://41.мвд.рф",
"callback":"qwerty"}
,{ "url":"http://41.мвд.рф",
"callback":"qwerty"}
,{ "url":"http://co-operate.ru",
"callback":"qwerty"}
,{ "url":"http://www.visitkamchatka.ru",
"callback":"qwerty"}
,{ "url":"http://garant.ru",
"callback":"qwerty"}
,{ "url":"http://infonika.net",
"callback":"qwerty"}
,{ "url":"http://rescue-kamchatka.ru",
"callback":"qwerty"}
,{ "url":"http://ads41.ru",
"callback":"qwerty"}
,{ "url":"http://всяеда41.рф",
"callback":"qwerty"}
,{ "url":"http://www.emspost.ru",
"callback":"qwerty"}
,{ "url":"http://сдэк-посылочка.рф | http://www.cdek.ru | http://www.edostavka.ru",
"callback":"qwerty"}
,{ "url":"http://tpprf.ru",
"callback":"qwerty"}
,{ "url":"http://loglab.ru",
"callback":"qwerty"}
,{ "url":"http://stilteks.ru",
"callback":"qwerty"}
,{ "url":"http://pk.gruzchikov-service.ru",
"callback":"qwerty"}
,{ "url":"http://www.kscm.ru",
"callback":"qwerty"}
,{ "url":"http://skservice.pro",
"callback":"qwerty"}
,{ "url":"http://www.kamfs.ru",
"callback":"qwerty"}
,{ "url":"http://vituskam.ru",
"callback":"qwerty"}
,{ "url":"http://rs-class.org",
"callback":"qwerty"}
,{ "url":"http://oaosvrc.ru",
"callback":"qwerty"}
,{ "url":"http://www.vost-tech.ru",
"callback":"qwerty"}
,{ "url":"http://openkam.ru",
"callback":"qwerty"}
,{ "url":"http://limo41.ru",
"callback":"qwerty"}
,{ "url":"http://limo41.ru",
"callback":"qwerty"}
,{ "url":"http://rubin41.ru",
"callback":"qwerty"}
,{ "url":"http://автопрокат41.рф",
"callback":"qwerty"}
,{ "url":"http://автопрокат-камчатка.рф",
"callback":"qwerty"}
,{ "url":"http://peliken.kia.ru | http://peliken.lada.ru",
"callback":"qwerty"}
,{ "url":"http://taxigost.ru",
"callback":"qwerty"}
,{ "url":"http://osagokam.ru",
"callback":"qwerty"}
,{ "url":"http://www.cargo41.com",
"callback":"qwerty"}
,{ "url":"http://alliance-auto.su",
"callback":"qwerty"}
,{ "url":"http://www.cargo41.com | http://www.cargo41.com",
"callback":"qwerty"}
,{ "url":"http://znakdv.ru",
"callback":"qwerty"}
,{ "url":"http://formula7.ru",
"callback":"qwerty"}
,{ "url":"http://www.port.kamchatka.ru",
"callback":"qwerty"}
,{ "url":"http://kamtrf.ucoz.ru",
"callback":"qwerty"}
,{ "url":"http://kamchattour.ru/transfer",
"callback":"qwerty"}
,{ "url":"http://easttour.ru",
"callback":"qwerty"}
,{ "url":"http://aliotkam.ru",
"callback":"qwerty"}
,{ "url":"http://marn-group.com",
"callback":"qwerty"}
,{ "url":"http://taxi.yandex.ru",
"callback":"qwerty"}
,{ "url":"http://taximaximapp.ru | http://www.taximaxim.com",
"callback":"qwerty"}
,{ "url":"http://autoprokat41.ru",
"callback":"qwerty"}
,{ "url":"http://taxigost.ru",
"callback":"qwerty"}
,{ "url":"http://kamchatka.vezitaxi.com",
"callback":"qwerty"}
,{ "url":"http://edem41.ru",
"callback":"qwerty"}
,{ "url":"http://kamprokat.ipkam.ru",
"callback":"qwerty"}
,{ "url":"http://kamchatka-volcan-tours.ru",
"callback":"qwerty"}
,{ "url":"http://autobuspk.ru",
"callback":"qwerty"}
,{ "url":"http://аист-групп.рф | http://aist-grupp.ru",
"callback":"qwerty"}
,{ "url":"http://www.rosslogistic.ru",
"callback":"qwerty"}
,{ "url":"http://fesco.ru",
"callback":"qwerty"}
,{ "url":"http://kasco.su",
"callback":"qwerty"}
,{ "url":"http://bagram.biz",
"callback":"qwerty"}
,{ "url":"http://jde.ru",
"callback":"qwerty"}
,{ "url":"http://www.sunmagadan.ru",
"callback":"qwerty"}
,{ "url":"http://www.biletur.ru",
"callback":"qwerty"}
,{ "url":"http://kavgs.ru",
"callback":"qwerty"}
,{ "url":"http://solar-wind.ru",
"callback":"qwerty"}
,{ "url":"http://kambilet.ru",
"callback":"qwerty"}
,{ "url":"http://www.kamavia.ru",
"callback":"qwerty"}
,{ "url":"http://www.expres-tur.ru",
"callback":"qwerty"}
,{ "url":"http://kamonline.ru | http://www.futen-kamchatka.ru",
"callback":"qwerty"}
,{ "url":"http://ru-voyage.com",
"callback":"qwerty"}
,{ "url":"http://skytour.pro | http://скайтур.рф",
"callback":"qwerty"}
,{ "url":"http://www.s7.ru",
"callback":"qwerty"}
,{ "url":"http://sov41.ru",
"callback":"qwerty"}
,{ "url":"http://кредитюрист.xn--p1ai/%D0%BF%D0%B5%D1%82%D1%80%D0%BE%D0%BF%D0%B0%D0%B2%D0%BB%D0%BE%D0%B2%D1%81%D0%BA",
"callback":"qwerty"}
,{ "url":"http://as-kamchatka.ru",
"callback":"qwerty"}
,{ "url":"http://uskkam.ru",
"callback":"qwerty"}
,{ "url":"http://urist41.ru",
"callback":"qwerty"}
,{ "url":"http://gosurburo41.ru",
"callback":"qwerty"}
,{ "url":"http://advokatkamchatka.ru",
"callback":"qwerty"}
,{ "url":"http://rcree.ru",
"callback":"qwerty"}
,{ "url":"http://expertiza41.ru",
"callback":"qwerty"}
,{ "url":"http://kamchatadvokat.ru",
"callback":"qwerty"}
,{ "url":"http://krkk.pro",
"callback":"qwerty"}
,{ "url":"http://erdc.ru",
"callback":"qwerty"}
,{ "url":"http://sogaz-med.ru",
"callback":"qwerty"}
,{ "url":"http://skgelios.ru",
"callback":"qwerty"}
,{ "url":"http://www.soglasie.ru",
"callback":"qwerty"}
,{ "url":"http://dalgaso.ru",
"callback":"qwerty"}
,{ "url":"http://www.rgs.ru",
"callback":"qwerty"}
,{ "url":"http://www.absolutins.ru",
"callback":"qwerty"}
,{ "url":"http://www.vsk.ru",
"callback":"qwerty"}
,{ "url":"http://kam-osago.ru",
"callback":"qwerty"}
,{ "url":"http://www.xocka.ru",
"callback":"qwerty"}
,{ "url":"http://rsk-sterh.ru",
"callback":"qwerty"}
,{ "url":"http://www.sogaz.ru",
"callback":"qwerty"}
,{ "url":"http://www.contact-sys.com",
"callback":"qwerty"}
,{ "url":"http://www.unistream.ru",
"callback":"qwerty"}
,{ "url":"http://koronapay.com",
"callback":"qwerty"}
,{ "url":"http://www.westernunion.ru",
"callback":"qwerty"}
,{ "url":"http://kamcq.ru",
"callback":"qwerty"}
,{ "url":"http://www.npssk.ru",
"callback":"qwerty"}
,{ "url":"http://banksovetnik.ru",
"callback":"qwerty"}
,{ "url":"http://центрконсалт.рф",
"callback":"qwerty"}
,{ "url":"http://кск-альянс.рф",
"callback":"qwerty"}
,{ "url":"http://кск-альянс.рф",
"callback":"qwerty"}
,{ "url":"http://garaji41.ru",
"callback":"qwerty"}
,{ "url":"http://karioko.ru",
"callback":"qwerty"}
,{ "url":"http://ros-dengi.ru",
"callback":"qwerty"}
,{ "url":"http://af-credit.ru",
"callback":"qwerty"}
,{ "url":"http://ex-dengi.com",
"callback":"qwerty"}
,{ "url":"http://www.otlnal.ru",
"callback":"qwerty"}
,{ "url":"http://5element-mfo.ru",
"callback":"qwerty"}
,{ "url":"http://avto-tema.com",
"callback":"qwerty"}
,{ "url":"http://www.kamfond.ru",
"callback":"qwerty"}
,{ "url":"http://www.lombard-union.ru",
"callback":"qwerty"}
,{ "url":"http://www.expoleasing.ru",
"callback":"qwerty"}
,{ "url":"http://www.sberfonds.ru",
"callback":"qwerty"}
,{ "url":"http://rosvoenipoteka.ru/",
"callback":"qwerty"}
,{ "url":"http://dvic.ru",
"callback":"qwerty"}
,{ "url":"http://www.kamipoteka.ru",
"callback":"qwerty"}
,{ "url":"http://hermes-ltd.com | http://bestwaycoop.com",
"callback":"qwerty"}
,{ "url":"http://содружество41.рф",
"callback":"qwerty"}
,{ "url":"http://law-alfa.business.site",
"callback":"qwerty"}
,{ "url":"http://nemesis-lex.ru",
"callback":"qwerty"}
,{ "url":"http://www.grand-lex.ru",
"callback":"qwerty"}
,{ "url":"http://прозакон-дв.рф",
"callback":"qwerty"}
,{ "url":"http://bankrot41.net",
"callback":"qwerty"}
,{ "url":"http://www.мойюрист41.рф",
"callback":"qwerty"}
,{ "url":"http://rayt41.ru",
"callback":"qwerty"}
,{ "url":"http://kollegia-kamchatka.ru",
"callback":"qwerty"}
,{ "url":"http://dejure41.ru",
"callback":"qwerty"}
,{ "url":"http://1vashbuhgalter.ru",
"callback":"qwerty"}
,{ "url":"http://www.consultdv.ru",
"callback":"qwerty"}
,{ "url":"http://www.legis41.ru",
"callback":"qwerty"}
,{ "url":"http://otchet-pk.ru",
"callback":"qwerty"}
,{ "url":"http://aksioplus.ru",
"callback":"qwerty"}
,{ "url":"http://ооо-контраст.рф | http://ooo-kontrast1.ru",
"callback":"qwerty"}
,{ "url":"http://sberbank.ru",
"callback":"qwerty"}
,{ "url":"http://www.sovcombank.ru",
"callback":"qwerty"}
,{ "url":"http://vostbank.ru",
"callback":"qwerty"}
,{ "url":"http://www.atb.su/?utm_source=2gis&utm_medium=special&utm_content=2gis_link&utm_campaign=2gis_link",
"callback":"qwerty"}
,{ "url":"http://www.vtb.ru | http://www.vtb24.ru",
"callback":"qwerty"}
,{ "url":"http://www.kkapb.ru",
"callback":"qwerty"}
,{ "url":"http://www.rshb.ru",
"callback":"qwerty"}
,{ "url":"http://www.rosbank.ru",
"callback":"qwerty"}
,{ "url":"http://www.pskb.com",
"callback":"qwerty"}
,{ "url":"http://rgsbank.ru",
"callback":"qwerty"}
,{ "url":"http://gazprombank.ru",
"callback":"qwerty"}
,{ "url":"http://delo.ru",
"callback":"qwerty"}
,{ "url":"http://www.mspbank.ru",
"callback":"qwerty"}
,{ "url":"http://www.bbr.ru",
"callback":"qwerty"}
,{ "url":"http://www.dvbank.ru",
"callback":"qwerty"}
,{ "url":"http://skbbank.ru",
"callback":"qwerty"}
,{ "url":"http://ad.admitad.com/g/47rub4kekvfb9df7f7905f4e53bb1306b4649ae1",
"callback":"qwerty"}
,{ "url":"http://www.pochtabank.ru",
"callback":"qwerty"}
,{ "url":"http://homecredit.ru",
"callback":"qwerty"}
,{ "url":"http://www.otpbank.ru",
"callback":"qwerty"}
,{ "url":"http://kamviz.ru",
"callback":"qwerty"}
,{ "url":"http://us-light.ru",
"callback":"qwerty"}
,{ "url":"http://4glaza.ru",
"callback":"qwerty"}
,{ "url":"http://csm41.ru",
"callback":"qwerty"}
,{ "url":"http://desprom.ru",
"callback":"qwerty"}
,{ "url":"http://www.whitecat.ru",
"callback":"qwerty"}
,{ "url":"http://razvitiekam.ru",
"callback":"qwerty"}
,{ "url":"http://www.nlstar.com",
"callback":"qwerty"}
,{ "url":"http://www.fire-bird.ru",
"callback":"qwerty"}
,{ "url":"http://chistokot41.ru",
"callback":"qwerty"}
,{ "url":"http://kanslertrade.ru",
"callback":"qwerty"}
,{ "url":"http://principe.my1.ru",
"callback":"qwerty"}
,{ "url":"http://www.novkniga.ru",
"callback":"qwerty"}
,{ "url":"http://www.novkniga.ru",
"callback":"qwerty"}
,{ "url":"http://www.novkniga.ru",
"callback":"qwerty"}
,{ "url":"http://www.novkniga.ru",
"callback":"qwerty"}
,{ "url":"http://www.novkniga.ru",
"callback":"qwerty"}
,{ "url":"http://www.novkniga.ru",
"callback":"qwerty"}
,{ "url":"http://www.aeroflot.ru",
"callback":"qwerty"}
,{ "url":"http://s7.ru",
"callback":"qwerty"}
,{ "url":"http://золотаякисть.рф",
"callback":"qwerty"}
,{ "url":"http://www.zolotorossii.com",
"callback":"qwerty"}
,{ "url":"http://golden-time.ru",
"callback":"qwerty"}
,{ "url":"http://золотаякисть.рф | http://золотаякисть.рф",
"callback":"qwerty"}
,{ "url":"http://золотаякисть.рф",
"callback":"qwerty"}
,{ "url":"http://sunlight.net",
"callback":"qwerty"}
,{ "url":"http://золотаякисть.рф",
"callback":"qwerty"}
,{ "url":"http://золотаякисть.рф",
"callback":"qwerty"}
,{ "url":"http://gold41.ru",
"callback":"qwerty"}
,{ "url":"http://pandora.net",
"callback":"qwerty"}
,{ "url":"http://kamrad.su",
"callback":"qwerty"}
,{ "url":"http://time41.ru",
"callback":"qwerty"}
,{ "url":"http://shamsa.net",
"callback":"qwerty"}
,{ "url":"http://galantsiti.ru",
"callback":"qwerty"}
,{ "url":"http://www.novkniga.ru",
"callback":"qwerty"}
,{ "url":"http://www.dialog41.ru",
"callback":"qwerty"}
,{ "url":"http://скрапенок.рф",
"callback":"qwerty"}
,{ "url":"http://www.novkniga.ru",
"callback":"qwerty"}
,{ "url":"http://www.novkniga.ru",
"callback":"qwerty"}
,{ "url":"http://чан41.рф",
"callback":"qwerty"}
,{ "url":"http://www.agrotek.ru",
"callback":"qwerty"}
,{ "url":"http://sofija.ru",
"callback":"qwerty"}
,{ "url":"http://biglion.ru",
"callback":"qwerty"}
,{ "url":"http://shik41.ru",
"callback":"qwerty"}
,{ "url":"http://master-i-margo.ru",
"callback":"qwerty"}
,{ "url":"http://www.tojiro.ru",
"callback":"qwerty"}
,{ "url":"http://gaga.ru",
"callback":"qwerty"}
,{ "url":"http://tvoi-mandarin.ru",
"callback":"qwerty"}
,{ "url":"http://market.shamsa.net",
"callback":"qwerty"}
,{ "url":"http://344005.ru",
"callback":"qwerty"}
,{ "url":"http://weddingkam.ru",
"callback":"qwerty"}
,{ "url":"http://cveti-kamchatka.ru",
"callback":"qwerty"}
,{ "url":"http://www.kamflo.ru",
"callback":"qwerty"}
,{ "url":"http://www.samberi.com",
"callback":"qwerty"}
,{ "url":"http://saveanimals41.ru",
"callback":"qwerty"}
,{ "url":"http://talisman-club.ru",
"callback":"qwerty"}
,{ "url":"http://www.osten.holypet.ru",
"callback":"qwerty"}
,{ "url":"http://volcanplace.ru",
"callback":"qwerty"}
,{ "url":"http://www.kainyran.ru",
"callback":"qwerty"}
,{ "url":"http://www.zooboom41.ru",
"callback":"qwerty"}
,{ "url":"http://furfur.vet",
"callback":"qwerty"}
,{ "url":"http://шпиц41.рф",
"callback":"qwerty"}
,{ "url":"http://Animal41.ru | http://city-pages.info/orgs/zhivotnye/animal",
"callback":"qwerty"}
,{ "url":"http://камчатский-ковчег.рф",
"callback":"qwerty"}
,{ "url":"http://мцрадужный.рф",
"callback":"qwerty"}
,{ "url":"http://мцрадужный.рф",
"callback":"qwerty"}
,{ "url":"http://kamvet.ru",
"callback":"qwerty"}
,{ "url":"http://domovid.ru",
"callback":"qwerty"}
,{ "url":"http://www.dekoroknapk.ru",
"callback":"qwerty"}
,{ "url":"http://domtkani.me",
"callback":"qwerty"}
,{ "url":"http://www.stylekam.ru",
"callback":"qwerty"}
,{ "url":"http://www.opt-electric.ru",
"callback":"qwerty"}
,{ "url":"http://poli-floor.ru",
"callback":"qwerty"}
,{ "url":"http://nepdiis.ru",
"callback":"qwerty"}
,{ "url":"http://krep-kam.ru",
"callback":"qwerty"}
,{ "url":"http://www.nashdomkam.ipkam.ru",
"callback":"qwerty"}
,{ "url":"http://megcomplex.ru",
"callback":"qwerty"}
,{ "url":"http://www.pk.alserostroy.ru",
"callback":"qwerty"}
,{ "url":"http://kam-light.nethouse.ru",
"callback":"qwerty"}
,{ "url":"http://kamexpocenter.ru",
"callback":"qwerty"}
,{ "url":"http://Www.lafasad.ru",
"callback":"qwerty"}
,{ "url":"http://petropavlovsk-kamchatskiy.ruplans.ru | http://www.ruplans.ru",
"callback":"qwerty"}
,{ "url":"http://engbur.ru",
"callback":"qwerty"}
,{ "url":"http://www.adm-avrora.ru",
"callback":"qwerty"}
,{ "url":"http://inchalet.net",
"callback":"qwerty"}
,{ "url":"http://41proekt.ru",
"callback":"qwerty"}
,{ "url":"http://kamgrp.ru",
"callback":"qwerty"}
,{ "url":"http://grupsm.ru",
"callback":"qwerty"}
,{ "url":"http://oaoegn.ru",
"callback":"qwerty"}
,{ "url":"http://dez-oao.ru",
"callback":"qwerty"}
,{ "url":"http://flat41.ru",
"callback":"qwerty"}
,{ "url":"http://kamreal.ru",
"callback":"qwerty"}
,{ "url":"http://www.kamcn.ru",
"callback":"qwerty"}
,{ "url":"http://garant-elizovo.ru",
"callback":"qwerty"}
,{ "url":"http://kam-fenix.ru",
"callback":"qwerty"}
,{ "url":"http://kappri.iks.ru",
"callback":"qwerty"}
,{ "url":"http://www.kamgrc.ru",
"callback":"qwerty"}
,{ "url":"http://an-kamriko.recrm.ru",
"callback":"qwerty"}
,{ "url":"http://www.gold-k.ru",
"callback":"qwerty"}
,{ "url":"http://centrkam.ru",
"callback":"qwerty"}
,{ "url":"http://максим-недвижимость.рф",
"callback":"qwerty"}
,{ "url":"http://www.roskam-n.ru",
"callback":"qwerty"}
,{ "url":"http://www.vostokn.ru",
"callback":"qwerty"}
,{ "url":"http://мойдом41.рф",
"callback":"qwerty"}
,{ "url":"http://avellum41.ru",
"callback":"qwerty"}
,{ "url":"http://www.anc-k.ru",
"callback":"qwerty"}
,{ "url":"http://rosnd.ru",
"callback":"qwerty"}
,{ "url":"http://www.gorod-dv.ru",
"callback":"qwerty"}
,{ "url":"http://kamregion.ru",
"callback":"qwerty"}
,{ "url":"http://www.kamblok.ru",
"callback":"qwerty"}
,{ "url":"http://alfapol-kam.ru",
"callback":"qwerty"}
,{ "url":"http://millenum.okna",
"callback":"qwerty"}
,{ "url":"http://svetlyi-dom-kamchatka.ru",
"callback":"qwerty"}
,{ "url":"http://www.francekam.ru",
"callback":"qwerty"}
,{ "url":"http://potolok-art.ru",
"callback":"qwerty"}
,{ "url":"http://kampotolki.ru",
"callback":"qwerty"}
,{ "url":"http://planetapotolkov.net | http://planetasveta41.ru",
"callback":"qwerty"}
,{ "url":"http://integra41.ru",
"callback":"qwerty"}
,{ "url":"http://geometrkam.ru",
"callback":"qwerty"}
,{ "url":"http://www.tikkurila.ru",
"callback":"qwerty"}
,{ "url":"http://www.mg41.ipkam.ru",
"callback":"qwerty"}
,{ "url":"http://monblanc25.ru/",
"callback":"qwerty"}
,{ "url":"http://eurocerama.su",
"callback":"qwerty"}
,{ "url":"http://master-des.ru",
"callback":"qwerty"}
,{ "url":"http://solo-3d.ru",
"callback":"qwerty"}
,{ "url":"http://полы41.рф",
"callback":"qwerty"}
,{ "url":"http://www.zitadel.net",
"callback":"qwerty"}
,{ "url":"http://www.zitadel.net",
"callback":"qwerty"}
,{ "url":"http://410089.ru",
"callback":"qwerty"}
,{ "url":"http://akfa-u.ru",
"callback":"qwerty"}
,{ "url":"http://barierpk41.ru",
"callback":"qwerty"}
,{ "url":"http://evrostil41.ru",
"callback":"qwerty"}
,{ "url":"http://dveri-yukka.ru",
"callback":"qwerty"}
,{ "url":"http://prestigeoknastroy.ru",
"callback":"qwerty"}
,{ "url":"http://www.alutech-group.com",
"callback":"qwerty"}
,{ "url":"http://bastion41.ru",
"callback":"qwerty"}
,{ "url":"http://www.gate-system.ru",
"callback":"qwerty"}
,{ "url":"http://doorhan41.ru",
"callback":"qwerty"}
,{ "url":"http://citadel41.ru",
"callback":"qwerty"}
,{ "url":"http://www.alutech-group.com | http://citadel41.ru",
"callback":"qwerty"}
,{ "url":"http://www.hoermann.ru",
"callback":"qwerty"}
,{ "url":"http://antigravityrussia.ru",
"callback":"qwerty"}
,{ "url":"http://kam4ahostel.wixsite.com/kam4a",
"callback":"qwerty"}
,{ "url":"http://hostel24.ru",
"callback":"qwerty"}
,{ "url":"http://guesthouse-avrora.ru",
"callback":"qwerty"}
,{ "url":"http://gymandspa.ru",
"callback":"qwerty"}
,{ "url":"http://www.dynamo.su",
"callback":"qwerty"}
,{ "url":"http://www.tobebear.ru",
"callback":"qwerty"}
,{ "url":"http://kamchatka.info",
"callback":"qwerty"}
,{ "url":"http://www.kamchatkahunting.com",
"callback":"qwerty"}
,{ "url":"http://kamchatkavip.ru",
"callback":"qwerty"}
,{ "url":"http://kamchatkatracks.com",
"callback":"qwerty"}
,{ "url":"http://www.kamchatkadventures.ru | http://kamchatka-vip.ru",
"callback":"qwerty"}
,{ "url":"http://www.sannikov.org",
"callback":"qwerty"}
,{ "url":"http://kamchatkatravel.net",
"callback":"qwerty"}
,{ "url":"http://kamsplav.ru",
"callback":"qwerty"}
,{ "url":"http://www.kaminfotour.ru",
"callback":"qwerty"}
,{ "url":"http://kamchatka-adventures.com",
"callback":"qwerty"}
,{ "url":"http://www.ftkam.ru",
"callback":"qwerty"}
,{ "url":"http://na-kamchatku.ru",
"callback":"qwerty"}
,{ "url":"http://Anextour.com",
"callback":"qwerty"}
,{ "url":"http://kamchatka.tez-tour.com",
"callback":"qwerty"}
,{ "url":"http://grizzly-kam.ru",
"callback":"qwerty"}
,{ "url":"http://kam-fishing.ru",
"callback":"qwerty"}
,{ "url":"http://bigriver.ru",
"callback":"qwerty"}
,{ "url":"http://essh1.elizovomr.ru",
"callback":"qwerty"}
,{ "url":"http://vilsport-school1.ru",
"callback":"qwerty"}
,{ "url":"http://vil2.ru",
"callback":"qwerty"}
,{ "url":"http://kamhockey.ru",
"callback":"qwerty"}
,{ "url":"http://zvezda.kamch.sportsng.ru",
"callback":"qwerty"}
,{ "url":"http://moroznaya.com",
"callback":"qwerty"}
,{ "url":"http://edinoborstva-kamchatka.ru",
"callback":"qwerty"}
,{ "url":"http://kamchess.ru",
"callback":"qwerty"}
,{ "url":"http://ренсинкай-айкидо.рф",
"callback":"qwerty"}
,{ "url":"http://www.karatekam.ru",
"callback":"qwerty"}
,{ "url":"http://supkamchatka.ru | http://KiteRide.pro",
"callback":"qwerty"}
,{ "url":"http://www.aikibudo.su",
"callback":"qwerty"}
,{ "url":"http://kambiathlon.ru",
"callback":"qwerty"}
,{ "url":"http://камтеннис.рф",
"callback":"qwerty"}
,{ "url":"http://kamtourfamily.com",
"callback":"qwerty"}
,{ "url":"http://www.crossbox41.ru",
"callback":"qwerty"}
,{ "url":"http://www.kamfok.ru",
"callback":"qwerty"}
,{ "url":"http://vitahit.ru",
"callback":"qwerty"}
,{ "url":"http://www.fit41.ru",
"callback":"qwerty"}
,{ "url":"http://strong41.ru",
"callback":"qwerty"}
,{ "url":"http://adidas.ru",
"callback":"qwerty"}
,{ "url":"http://www.sportmaster.ru",
"callback":"qwerty"}
,{ "url":"http://fitness.reebok.ru | http://www.reebok.ru",
"callback":"qwerty"}
,{ "url":"http://fishka41.ru",
"callback":"qwerty"}
,{ "url":"http://sporshev.ru",
"callback":"qwerty"}
,{ "url":"http://www.snejnybars.ru",
"callback":"qwerty"}
,{ "url":"http://www.kamchatjeeptour.ru",
"callback":"qwerty"}
,{ "url":"http://kamchatkavizit.ru",
"callback":"qwerty"}
,{ "url":"http://freelanceguides.ru",
"callback":"qwerty"}
,{ "url":"http://www.kamchattour.ru | http://kamchattour.com",
"callback":"qwerty"}
,{ "url":"http://triptokamchatka.com",
"callback":"qwerty"}
,{ "url":"http://www.kamchatkawinter.com | http://allaboutkamchatka.ru",
"callback":"qwerty"}
,{ "url":"http://kamtour.com",
"callback":"qwerty"}
,{ "url":"http://petropavlovsk-hotel.ru",
"callback":"qwerty"}
,{ "url":"http://www.utes.net.ru",
"callback":"qwerty"}
,{ "url":"http://ist-travel.ru",
"callback":"qwerty"}
,{ "url":"http://kam.travel",
"callback":"qwerty"}
,{ "url":"http://volcanoesland.ru | http://volcanoesland.com",
"callback":"qwerty"}
,{ "url":"http://travelonkamchatka.ru",
"callback":"qwerty"}
,{ "url":"http://polusm.ru",
"callback":"qwerty"}
,{ "url":"http://voyage41.ru",
"callback":"qwerty"}
,{ "url":"http://www.omega-tours.ru",
"callback":"qwerty"}
,{ "url":"http://realkamchatka.com",
"callback":"qwerty"}
,{ "url":"http://vityaz.travel",
"callback":"qwerty"}
,{ "url":"http://kamchatkaforyou.com",
"callback":"qwerty"}
,{ "url":"http://www.armenycasa.ru",
"callback":"qwerty"}
,{ "url":"http://dancesport41.ru",
"callback":"qwerty"}
,{ "url":"http://www.dance-favorit.ru",
"callback":"qwerty"}
,{ "url":"http://schoolballet.com",
"callback":"qwerty"}
,{ "url":"http://vil2.ru",
"callback":"qwerty"}
,{ "url":"http://kamhockey.ru",
"callback":"qwerty"}
,{ "url":"http://kamchatkadiving.ru",
"callback":"qwerty"}
,{ "url":"http://sirena-kamtour.com",
"callback":"qwerty"}
,{ "url":"http://www.regionkamtur.com",
"callback":"qwerty"}
,{ "url":"http://kamchadal.pro",
"callback":"qwerty"}
,{ "url":"http://www.peleken.ru",
"callback":"qwerty"}
,{ "url":"http://www.kamtrekking.ru",
"callback":"qwerty"}
,{ "url":"http://firstkamtravel.ru",
"callback":"qwerty"}
,{ "url":"http://iamkamchatka.com",
"callback":"qwerty"}
,{ "url":"http://www.kam-cat.ru",
"callback":"qwerty"}
,{ "url":"http://www.kamchatka-tour.com",
"callback":"qwerty"}
,{ "url":"http://bankturov.ru",
"callback":"qwerty"}
,{ "url":"http://breeze41.ru",
"callback":"qwerty"}
,{ "url":"http://bigriver.ru | http://kingsalmon.ru",
"callback":"qwerty"}
,{ "url":"http://www.tourismkamchatka.com",
"callback":"qwerty"}
,{ "url":"http://5zvezdpk.ru",
"callback":"qwerty"}
,{ "url":"http://kantri41.ru | http://kantry.house",
"callback":"qwerty"}
,{ "url":"http://abazhurhotel.com",
"callback":"qwerty"}
,{ "url":"http://kamdut.ru",
"callback":"qwerty"}
,{ "url":"http://kutkhs-house.umitpk.ru/",
"callback":"qwerty"}
,{ "url":"http://arthotel-kamchatka.ru",
"callback":"qwerty"}
,{ "url":"http://dolcevita-hotel.ru",
"callback":"qwerty"}
,{ "url":"http://barhat.house",
"callback":"qwerty"}
,{ "url":"http://www.nk-hotel.ru",
"callback":"qwerty"}
,{ "url":"http://www.avachahotel.ru",
"callback":"qwerty"}
,{ "url":"http://dosaaf41region.ru",
"callback":"qwerty"}
,{ "url":"http://kam-chempion.ru",
"callback":"qwerty"}
,{ "url":"http://hotellook.ru",
"callback":"qwerty"}
,{ "url":"http://mgp.ru",
"callback":"qwerty"}
,{ "url":"http://www.visatravel.bz",
"callback":"qwerty"}
,{ "url":"http://airkam.pro",
"callback":"qwerty"}
,{ "url":"http://камтеннис.рф",
"callback":"qwerty"}
,{ "url":"http://elizovofok.ru",
"callback":"qwerty"}
,{ "url":"http://dreamkam.ru",
"callback":"qwerty"}
,{ "url":"http://www.snowave-kamchatka.com",
"callback":"qwerty"}
,{ "url":"http://www.kamchatintour.ru",
"callback":"qwerty"}
,{ "url":"http://nachiki41.ru",
"callback":"qwerty"}
,{ "url":"http://www.dreamkam.ru",
"callback":"qwerty"}
,{ "url":"http://snow-valley.ru",
"callback":"qwerty"}
,{ "url":"http://www.snowdogskamchatka.ru",
"callback":"qwerty"}
,{ "url":"http://www.booking.com/hotel/ru/swiss-chalet-in-kamchatka.html",
"callback":"qwerty"}
,{ "url":"http://kamrosinka.ru",
"callback":"qwerty"}
,{ "url":"http://zolotarevfoto.ru",
"callback":"qwerty"}
,{ "url":"http://www.izumrud41.ucoz.ru",
"callback":"qwerty"}
,{ "url":"http://1mt.ru",
"callback":"qwerty"}
,{ "url":"http://skorohod41.ru",
"callback":"qwerty"}
,{ "url":"http://norma.ipkam.ru",
"callback":"qwerty"}
,{ "url":"http://www.retrofm.ru",
"callback":"qwerty"}
,{ "url":"http://rusradio.ru",
"callback":"qwerty"}
,{ "url":"http://europaplus.ru",
"callback":"qwerty"}
,{ "url":"http://avtoradiokamchatka.ru",
"callback":"qwerty"}
,{ "url":"http://radio41.ru",
"callback":"qwerty"}
,{ "url":"http://radiosv.com",
"callback":"qwerty"}
,{ "url":"http://kamtroyka.ru",
"callback":"qwerty"}
,{ "url":"http://potolok41tk.ru",
"callback":"qwerty"}
,{ "url":"http://digigrafica.ru",
"callback":"qwerty"}
,{ "url":"http://kamchatka-2.ru",
"callback":"qwerty"}
,{ "url":"http://kamchatpress.ru",
"callback":"qwerty"}
,{ "url":"http://cnti41.ru",
"callback":"qwerty"}
,{ "url":"http://pressa41.ru",
"callback":"qwerty"}
,{ "url":"http://handmadesuvenir.ucoz.ru",
"callback":"qwerty"}
,{ "url":"http://whiteline.su",
"callback":"qwerty"}
,{ "url":"http://www.novkniga.ru",
"callback":"qwerty"}
,{ "url":"http://www.333art.ru",
"callback":"qwerty"}
,{ "url":"http://kamchatka-explorer.com",
"callback":"qwerty"}
,{ "url":"http://reklama-exe.ru",
"callback":"qwerty"}
,{ "url":"http://spformat.ru",
"callback":"qwerty"}
,{ "url":"http://era41.ru",
"callback":"qwerty"}
,{ "url":"http://ralift.pro",
"callback":"qwerty"}
,{ "url":"http://gazetasrochno.ru",
"callback":"qwerty"}
,{ "url":"http://profkam.ru",
"callback":"qwerty"}
,{ "url":"http://prof41.ru",
"callback":"qwerty"}
,{ "url":"http://lplus.ru",
"callback":"qwerty"}
,{ "url":"http://kamtime.ru",
"callback":"qwerty"}
,{ "url":"http://mk.ru",
"callback":"qwerty"}
,{ "url":"http://www.kamvesti.com | http://radio3.ru",
"callback":"qwerty"}
,{ "url":"http://chaspik41.ru",
"callback":"qwerty"}
,{ "url":"http://kp.ru",
"callback":"qwerty"}
,{ "url":"http://вдобрыеруки.рф",
"callback":"qwerty"}
,{ "url":"http://41dom.ru",
"callback":"qwerty"}
,{ "url":"http://aif.ru",
"callback":"qwerty"}
,{ "url":"http://shans.me",
"callback":"qwerty"}
,{ "url":"http://lplus.ru",
"callback":"qwerty"}
,{ "url":"http://petro-video.tv",
"callback":"qwerty"}
,{ "url":"http://ural-press.ru",
"callback":"qwerty"}
,{ "url":"http://kabim.ru",
"callback":"qwerty"}
,{ "url":"http://reklamatranzit.ru",
"callback":"qwerty"}
,{ "url":"http://reklamapk.ru",
"callback":"qwerty"}
,{ "url":"http://reklamaplus.pro",
"callback":"qwerty"}
]